{
  "exp": "mae_har_ep300_mask0.5_strategyrandom_ph29pw25_seed42_enc12_dim128_bs128",
  "args": {
    "epochs": 300,
    "mask_ratio": 0.5,
    "encoder_depth": 12,
    "encoder_dim": 128,
    "decoder_dim": 64,
    "batch_size": 128,
    "lr": 0.00015,
    "eval_layers": "1,3,6,9,12",
    "eval_every": 50,
    "mask_strategy": "random",
    "patch_h": 29,
    "patch_w": 25,
    "seed": 42
  },
  "loss_log": [
    {
      "epoch": 1,
      "loss": 0.9323631755652881
    },
    {
      "epoch": 2,
      "loss": 0.49079285703954245
    },
    {
      "epoch": 3,
      "loss": 0.42315594231088954
    },
    {
      "epoch": 4,
      "loss": 0.39617597897137913
    },
    {
      "epoch": 5,
      "loss": 0.36685694097763016
    },
    {
      "epoch": 6,
      "loss": 0.3307880691829182
    },
    {
      "epoch": 7,
      "loss": 0.29861007453430266
    },
    {
      "epoch": 8,
      "loss": 0.27524615868571256
    },
    {
      "epoch": 9,
      "loss": 0.2532973384395951
    },
    {
      "epoch": 10,
      "loss": 0.231647793824474
    },
    {
      "epoch": 11,
      "loss": 0.21424913308804944
    },
    {
      "epoch": 12,
      "loss": 0.2013133263126725
    },
    {
      "epoch": 13,
      "loss": 0.1913681063978445
    },
    {
      "epoch": 14,
      "loss": 0.18227694680293402
    },
    {
      "epoch": 15,
      "loss": 0.17632253459166913
    },
    {
      "epoch": 16,
      "loss": 0.17028882460934774
    },
    {
      "epoch": 17,
      "loss": 0.16543476265810786
    },
    {
      "epoch": 18,
      "loss": 0.16263798686365286
    },
    {
      "epoch": 19,
      "loss": 0.15782796742305868
    },
    {
      "epoch": 20,
      "loss": 0.15449545581248544
    },
    {
      "epoch": 21,
      "loss": 0.15098586869204328
    },
    {
      "epoch": 22,
      "loss": 0.14852102300418274
    },
    {
      "epoch": 23,
      "loss": 0.14521600926915804
    },
    {
      "epoch": 24,
      "loss": 0.14262874841335274
    },
    {
      "epoch": 25,
      "loss": 0.13994348403953372
    },
    {
      "epoch": 26,
      "loss": 0.13798492379663957
    },
    {
      "epoch": 27,
      "loss": 0.1356866585002059
    },
    {
      "epoch": 28,
      "loss": 0.13437837113936743
    },
    {
      "epoch": 29,
      "loss": 0.13263190715085893
    },
    {
      "epoch": 30,
      "loss": 0.13169664388433808
    },
    {
      "epoch": 31,
      "loss": 0.13058266509324312
    },
    {
      "epoch": 32,
      "loss": 0.12992530262895993
    },
    {
      "epoch": 33,
      "loss": 0.1287927216007596
    },
    {
      "epoch": 34,
      "loss": 0.128346045235438
    },
    {
      "epoch": 35,
      "loss": 0.12773851433857566
    },
    {
      "epoch": 36,
      "loss": 0.12753787663366115
    },
    {
      "epoch": 37,
      "loss": 0.1264377868335162
    },
    {
      "epoch": 38,
      "loss": 0.1262294878917081
    },
    {
      "epoch": 39,
      "loss": 0.12582724829692216
    },
    {
      "epoch": 40,
      "loss": 0.12544364149549178
    },
    {
      "epoch": 41,
      "loss": 0.12496848506409497
    },
    {
      "epoch": 42,
      "loss": 0.12471570766397885
    },
    {
      "epoch": 43,
      "loss": 0.12446675307693936
    },
    {
      "epoch": 44,
      "loss": 0.12411013986205771
    },
    {
      "epoch": 45,
      "loss": 0.12404595754508461
    },
    {
      "epoch": 46,
      "loss": 0.12369618853110642
    },
    {
      "epoch": 47,
      "loss": 0.12331141256505534
    },
    {
      "epoch": 48,
      "loss": 0.12277264147996902
    },
    {
      "epoch": 49,
      "loss": 0.1228097149924863
    },
    {
      "epoch": 50,
      "loss": 0.12252956739671174
    },
    {
      "epoch": 51,
      "loss": 0.1222771695770678
    },
    {
      "epoch": 52,
      "loss": 0.12207512140628837
    },
    {
      "epoch": 53,
      "loss": 0.12175459290544192
    },
    {
      "epoch": 54,
      "loss": 0.12162129678541705
    },
    {
      "epoch": 55,
      "loss": 0.12140586604142473
    },
    {
      "epoch": 56,
      "loss": 0.12121985160878726
    },
    {
      "epoch": 57,
      "loss": 0.12091442490262645
    },
    {
      "epoch": 58,
      "loss": 0.12093343186591353
    },
    {
      "epoch": 59,
      "loss": 0.1208228108783563
    },
    {
      "epoch": 60,
      "loss": 0.12076514245321353
    },
    {
      "epoch": 61,
      "loss": 0.12032136108194079
    },
    {
      "epoch": 62,
      "loss": 0.12031466766659703
    },
    {
      "epoch": 63,
      "loss": 0.1201193148181552
    },
    {
      "epoch": 64,
      "loss": 0.12001098266669682
    },
    {
      "epoch": 65,
      "loss": 0.11977006858658223
    },
    {
      "epoch": 66,
      "loss": 0.11977783692557187
    },
    {
      "epoch": 67,
      "loss": 0.1197584436408111
    },
    {
      "epoch": 68,
      "loss": 0.11972777133009263
    },
    {
      "epoch": 69,
      "loss": 0.11932706651056096
    },
    {
      "epoch": 70,
      "loss": 0.11943443483185201
    },
    {
      "epoch": 71,
      "loss": 0.11927989009945165
    },
    {
      "epoch": 72,
      "loss": 0.11922132365760349
    },
    {
      "epoch": 73,
      "loss": 0.11910049515288501
    },
    {
      "epoch": 74,
      "loss": 0.11912469947267146
    },
    {
      "epoch": 75,
      "loss": 0.11900977395652305
    },
    {
      "epoch": 76,
      "loss": 0.11877969235536598
    },
    {
      "epoch": 77,
      "loss": 0.11877844327439864
    },
    {
      "epoch": 78,
      "loss": 0.11865808548671859
    },
    {
      "epoch": 79,
      "loss": 0.11874169971616495
    },
    {
      "epoch": 80,
      "loss": 0.11853628587864694
    },
    {
      "epoch": 81,
      "loss": 0.11872583911532447
    },
    {
      "epoch": 82,
      "loss": 0.11859795681777455
    },
    {
      "epoch": 83,
      "loss": 0.1185767494940332
    },
    {
      "epoch": 84,
      "loss": 0.11833183205730859
    },
    {
      "epoch": 85,
      "loss": 0.11828124412291106
    },
    {
      "epoch": 86,
      "loss": 0.11832989503939946
    },
    {
      "epoch": 87,
      "loss": 0.11824473241964976
    },
    {
      "epoch": 88,
      "loss": 0.11812591260032994
    },
    {
      "epoch": 89,
      "loss": 0.11816044391265937
    },
    {
      "epoch": 90,
      "loss": 0.11816577644397815
    },
    {
      "epoch": 91,
      "loss": 0.11809862573586759
    },
    {
      "epoch": 92,
      "loss": 0.11789781981635661
    },
    {
      "epoch": 93,
      "loss": 0.11795373655678261
    },
    {
      "epoch": 94,
      "loss": 0.11804459097662143
    },
    {
      "epoch": 95,
      "loss": 0.11785881784522817
    },
    {
      "epoch": 96,
      "loss": 0.11789126068885837
    },
    {
      "epoch": 97,
      "loss": 0.11786035656751621
    },
    {
      "epoch": 98,
      "loss": 0.11772111896425486
    },
    {
      "epoch": 99,
      "loss": 0.11760716051572845
    },
    {
      "epoch": 100,
      "loss": 0.11771064442360685
    },
    {
      "epoch": 101,
      "loss": 0.1177789732547743
    },
    {
      "epoch": 102,
      "loss": 0.11749628181791022
    },
    {
      "epoch": 103,
      "loss": 0.11761377051117874
    },
    {
      "epoch": 104,
      "loss": 0.11754524073607865
    },
    {
      "epoch": 105,
      "loss": 0.11756282321931351
    },
    {
      "epoch": 106,
      "loss": 0.11746621650776692
    },
    {
      "epoch": 107,
      "loss": 0.11757668923764002
    },
    {
      "epoch": 108,
      "loss": 0.1173338352126025
    },
    {
      "epoch": 109,
      "loss": 0.11749006453014556
    },
    {
      "epoch": 110,
      "loss": 0.1174311198826347
    },
    {
      "epoch": 111,
      "loss": 0.11731856094584578
    },
    {
      "epoch": 112,
      "loss": 0.11740151557716585
    },
    {
      "epoch": 113,
      "loss": 0.11725001347561677
    },
    {
      "epoch": 114,
      "loss": 0.11727609990962914
    },
    {
      "epoch": 115,
      "loss": 0.11713554940762974
    },
    {
      "epoch": 116,
      "loss": 0.11714350760337852
    },
    {
      "epoch": 117,
      "loss": 0.11720130330927316
    },
    {
      "epoch": 118,
      "loss": 0.11710715967984427
    },
    {
      "epoch": 119,
      "loss": 0.11709275167612802
    },
    {
      "epoch": 120,
      "loss": 0.1170446015894413
    },
    {
      "epoch": 121,
      "loss": 0.11716851139707225
    },
    {
      "epoch": 122,
      "loss": 0.11694806676712774
    },
    {
      "epoch": 123,
      "loss": 0.11710539211829503
    },
    {
      "epoch": 124,
      "loss": 0.11700252474596103
    },
    {
      "epoch": 125,
      "loss": 0.11690502937528349
    },
    {
      "epoch": 126,
      "loss": 0.11691588380684455
    },
    {
      "epoch": 127,
      "loss": 0.11695551317894742
    },
    {
      "epoch": 128,
      "loss": 0.11691098642491159
    },
    {
      "epoch": 129,
      "loss": 0.11684551812885773
    },
    {
      "epoch": 130,
      "loss": 0.11682161555758544
    },
    {
      "epoch": 131,
      "loss": 0.11683105473362264
    },
    {
      "epoch": 132,
      "loss": 0.1168497439828657
    },
    {
      "epoch": 133,
      "loss": 0.11685059228468508
    },
    {
      "epoch": 134,
      "loss": 0.11664728611885082
    },
    {
      "epoch": 135,
      "loss": 0.11673609739435571
    },
    {
      "epoch": 136,
      "loss": 0.11663549375675973
    },
    {
      "epoch": 137,
      "loss": 0.11664576243077006
    },
    {
      "epoch": 138,
      "loss": 0.11672695579805545
    },
    {
      "epoch": 139,
      "loss": 0.11678033636971599
    },
    {
      "epoch": 140,
      "loss": 0.11666232134614672
    },
    {
      "epoch": 141,
      "loss": 0.11671011925985415
    },
    {
      "epoch": 142,
      "loss": 0.11681250939589172
    },
    {
      "epoch": 143,
      "loss": 0.11666594348138287
    },
    {
      "epoch": 144,
      "loss": 0.1166271645841854
    },
    {
      "epoch": 145,
      "loss": 0.11653226795828059
    },
    {
      "epoch": 146,
      "loss": 0.1164080412348821
    },
    {
      "epoch": 147,
      "loss": 0.11658434463398797
    },
    {
      "epoch": 148,
      "loss": 0.11646993174439385
    },
    {
      "epoch": 149,
      "loss": 0.11647562562887158
    },
    {
      "epoch": 150,
      "loss": 0.11649540394899391
    },
    {
      "epoch": 151,
      "loss": 0.11641572522265571
    },
    {
      "epoch": 152,
      "loss": 0.11642603833405744
    },
    {
      "epoch": 153,
      "loss": 0.11648894207818168
    },
    {
      "epoch": 154,
      "loss": 0.11645736824721098
    },
    {
      "epoch": 155,
      "loss": 0.11639854644558259
    },
    {
      "epoch": 156,
      "loss": 0.11653785988511074
    },
    {
      "epoch": 157,
      "loss": 0.11639980931899377
    },
    {
      "epoch": 158,
      "loss": 0.11624349188059568
    },
    {
      "epoch": 159,
      "loss": 0.1163180454057597
    },
    {
      "epoch": 160,
      "loss": 0.1163273775683982
    },
    {
      "epoch": 161,
      "loss": 0.11636153089680842
    },
    {
      "epoch": 162,
      "loss": 0.11621821769291446
    },
    {
      "epoch": 163,
      "loss": 0.11624407941209418
    },
    {
      "epoch": 164,
      "loss": 0.11624601700653632
    },
    {
      "epoch": 165,
      "loss": 0.11627487891486712
    },
    {
      "epoch": 166,
      "loss": 0.11616101186899912
    },
    {
      "epoch": 167,
      "loss": 0.11609146819405612
    },
    {
      "epoch": 168,
      "loss": 0.1161008525994562
    },
    {
      "epoch": 169,
      "loss": 0.11627865276698555
    },
    {
      "epoch": 170,
      "loss": 0.11621414799065817
    },
    {
      "epoch": 171,
      "loss": 0.11616346847620748
    },
    {
      "epoch": 172,
      "loss": 0.11602989131850856
    },
    {
      "epoch": 173,
      "loss": 0.11609782092273235
    },
    {
      "epoch": 174,
      "loss": 0.1160205513504999
    },
    {
      "epoch": 175,
      "loss": 0.1161075190064453
    },
    {
      "epoch": 176,
      "loss": 0.11604225857272035
    },
    {
      "epoch": 177,
      "loss": 0.11613765948762496
    },
    {
      "epoch": 178,
      "loss": 0.11603905451262281
    },
    {
      "epoch": 179,
      "loss": 0.11611338478646108
    },
    {
      "epoch": 180,
      "loss": 0.11610519101044961
    },
    {
      "epoch": 181,
      "loss": 0.1159578167966434
    },
    {
      "epoch": 182,
      "loss": 0.11608796637682688
    },
    {
      "epoch": 183,
      "loss": 0.11596741664799906
    },
    {
      "epoch": 184,
      "loss": 0.11605460187863736
    },
    {
      "epoch": 185,
      "loss": 0.116015893407166
    },
    {
      "epoch": 186,
      "loss": 0.11599252368545249
    },
    {
      "epoch": 187,
      "loss": 0.115953645358483
    },
    {
      "epoch": 188,
      "loss": 0.11583776066878013
    },
    {
      "epoch": 189,
      "loss": 0.11594130254040162
    },
    {
      "epoch": 190,
      "loss": 0.1159040970905196
    },
    {
      "epoch": 191,
      "loss": 0.11580554724094413
    },
    {
      "epoch": 192,
      "loss": 0.11595108227006026
    },
    {
      "epoch": 193,
      "loss": 0.11592711082526616
    },
    {
      "epoch": 194,
      "loss": 0.1158517205289432
    },
    {
      "epoch": 195,
      "loss": 0.11577795685401984
    },
    {
      "epoch": 196,
      "loss": 0.11586036533117294
    },
    {
      "epoch": 197,
      "loss": 0.11580365235429435
    },
    {
      "epoch": 198,
      "loss": 0.11574563583625215
    },
    {
      "epoch": 199,
      "loss": 0.11560523487804901
    },
    {
      "epoch": 200,
      "loss": 0.11581840219774417
    },
    {
      "epoch": 201,
      "loss": 0.11588622190590415
    },
    {
      "epoch": 202,
      "loss": 0.11589040891045616
    },
    {
      "epoch": 203,
      "loss": 0.11576889801238265
    },
    {
      "epoch": 204,
      "loss": 0.11563348246827013
    },
    {
      "epoch": 205,
      "loss": 0.11579222697764635
    },
    {
      "epoch": 206,
      "loss": 0.11572448558928002
    },
    {
      "epoch": 207,
      "loss": 0.11565620798085417
    },
    {
      "epoch": 208,
      "loss": 0.11555276207980655
    },
    {
      "epoch": 209,
      "loss": 0.1155357671724189
    },
    {
      "epoch": 210,
      "loss": 0.11565279109137398
    },
    {
      "epoch": 211,
      "loss": 0.11555713122444493
    },
    {
      "epoch": 212,
      "loss": 0.11568054255275499
    },
    {
      "epoch": 213,
      "loss": 0.11547418586200192
    },
    {
      "epoch": 214,
      "loss": 0.11571619841491892
    },
    {
      "epoch": 215,
      "loss": 0.11573014434959207
    },
    {
      "epoch": 216,
      "loss": 0.11557122829946734
    },
    {
      "epoch": 217,
      "loss": 0.11558008189534857
    },
    {
      "epoch": 218,
      "loss": 0.11566293984651566
    },
    {
      "epoch": 219,
      "loss": 0.11568294749373481
    },
    {
      "epoch": 220,
      "loss": 0.11554001005632537
    },
    {
      "epoch": 221,
      "loss": 0.11558071053808644
    },
    {
      "epoch": 222,
      "loss": 0.11548845563083887
    },
    {
      "epoch": 223,
      "loss": 0.11560033448040485
    },
    {
      "epoch": 224,
      "loss": 0.11559825647799742
    },
    {
      "epoch": 225,
      "loss": 0.11550837027884665
    },
    {
      "epoch": 226,
      "loss": 0.11548863098557506
    },
    {
      "epoch": 227,
      "loss": 0.11551473276423556
    },
    {
      "epoch": 228,
      "loss": 0.11545771839363235
    },
    {
      "epoch": 229,
      "loss": 0.11544518030825116
    },
    {
      "epoch": 230,
      "loss": 0.11530823455679984
    },
    {
      "epoch": 231,
      "loss": 0.11547296259197451
    },
    {
      "epoch": 232,
      "loss": 0.11526222473808698
    },
    {
      "epoch": 233,
      "loss": 0.11542099585667961
    },
    {
      "epoch": 234,
      "loss": 0.11562409424888236
    },
    {
      "epoch": 235,
      "loss": 0.11539164216568072
    },
    {
      "epoch": 236,
      "loss": 0.11536866648211366
    },
    {
      "epoch": 237,
      "loss": 0.11551743830066352
    },
    {
      "epoch": 238,
      "loss": 0.11551164964302665
    },
    {
      "epoch": 239,
      "loss": 0.11552014703019745
    },
    {
      "epoch": 240,
      "loss": 0.1154953751358248
    },
    {
      "epoch": 241,
      "loss": 0.11548836529254913
    },
    {
      "epoch": 242,
      "loss": 0.11547133109221856
    },
    {
      "epoch": 243,
      "loss": 0.11550237646415121
    },
    {
      "epoch": 244,
      "loss": 0.11536725849977561
    },
    {
      "epoch": 245,
      "loss": 0.11533501979318403
    },
    {
      "epoch": 246,
      "loss": 0.11541406983243567
    },
    {
      "epoch": 247,
      "loss": 0.11540145129852351
    },
    {
      "epoch": 248,
      "loss": 0.11530092828685329
    },
    {
      "epoch": 249,
      "loss": 0.11526083839791161
    },
    {
      "epoch": 250,
      "loss": 0.1152844253395285
    },
    {
      "epoch": 251,
      "loss": 0.11533322540067491
    },
    {
      "epoch": 252,
      "loss": 0.11531849201059058
    },
    {
      "epoch": 253,
      "loss": 0.11540451725678784
    },
    {
      "epoch": 254,
      "loss": 0.11531991445060287
    },
    {
      "epoch": 255,
      "loss": 0.11524244260397695
    },
    {
      "epoch": 256,
      "loss": 0.11528786404856614
    },
    {
      "epoch": 257,
      "loss": 0.11529072742199614
    },
    {
      "epoch": 258,
      "loss": 0.1151362569293096
    },
    {
      "epoch": 259,
      "loss": 0.11533251990165029
    },
    {
      "epoch": 260,
      "loss": 0.11524051188358239
    },
    {
      "epoch": 261,
      "loss": 0.11530112466287046
    },
    {
      "epoch": 262,
      "loss": 0.11523699414517198
    },
    {
      "epoch": 263,
      "loss": 0.11536173628909248
    },
    {
      "epoch": 264,
      "loss": 0.11523755280567068
    },
    {
      "epoch": 265,
      "loss": 0.11541937074313562
    },
    {
      "epoch": 266,
      "loss": 0.11524268638874803
    },
    {
      "epoch": 267,
      "loss": 0.11523771015483708
    },
    {
      "epoch": 268,
      "loss": 0.11528383434883185
    },
    {
      "epoch": 269,
      "loss": 0.11534623189696244
    },
    {
      "epoch": 270,
      "loss": 0.11529101897031069
    },
    {
      "epoch": 271,
      "loss": 0.11522978668411572
    },
    {
      "epoch": 272,
      "loss": 0.11527916327828452
    },
    {
      "epoch": 273,
      "loss": 0.11533361229868162
    },
    {
      "epoch": 274,
      "loss": 0.11516610595087211
    },
    {
      "epoch": 275,
      "loss": 0.11525052941093843
    },
    {
      "epoch": 276,
      "loss": 0.11533158747035832
    },
    {
      "epoch": 277,
      "loss": 0.11512782442427817
    },
    {
      "epoch": 278,
      "loss": 0.11523661363337721
    },
    {
      "epoch": 279,
      "loss": 0.11518795721765075
    },
    {
      "epoch": 280,
      "loss": 0.1152798439420405
    },
    {
      "epoch": 281,
      "loss": 0.1152251942881516
    },
    {
      "epoch": 282,
      "loss": 0.11511957623241913
    },
    {
      "epoch": 283,
      "loss": 0.11527164409025795
    },
    {
      "epoch": 284,
      "loss": 0.11532264641885247
    },
    {
      "epoch": 285,
      "loss": 0.11524615560968716
    },
    {
      "epoch": 286,
      "loss": 0.11525657214224339
    },
    {
      "epoch": 287,
      "loss": 0.1152050458338289
    },
    {
      "epoch": 288,
      "loss": 0.11514269622663657
    },
    {
      "epoch": 289,
      "loss": 0.11525051686025801
    },
    {
      "epoch": 290,
      "loss": 0.11523224125128417
    },
    {
      "epoch": 291,
      "loss": 0.11520298712310337
    },
    {
      "epoch": 292,
      "loss": 0.11528292049964269
    },
    {
      "epoch": 293,
      "loss": 0.115220906345972
    },
    {
      "epoch": 294,
      "loss": 0.11519999012705825
    },
    {
      "epoch": 295,
      "loss": 0.11539544200613386
    },
    {
      "epoch": 296,
      "loss": 0.1151706028197493
    },
    {
      "epoch": 297,
      "loss": 0.1152157619418133
    },
    {
      "epoch": 298,
      "loss": 0.11527515947818756
    },
    {
      "epoch": 299,
      "loss": 0.11521967469404142
    },
    {
      "epoch": 300,
      "loss": 0.11521495036071255
    }
  ],
  "evals": {
    "epoch_50": {
      "layer_1": {
        "test_id": {
          "knn_acc": 0.9300304055213928,
          "knn_f1": 0.929461192627364,
          "lp_acc": 0.5217297077178955,
          "lp_f1": 0.37952731232225867
        },
        "test_cross_device": {
          "knn_acc": 0.2681964635848999,
          "knn_f1": 0.27872498421526926,
          "lp_acc": 0.5155227780342102,
          "lp_f1": 0.36165448519113863
        },
        "test_cross_env": {
          "knn_acc": 0.4305263161659241,
          "knn_f1": 0.40814185845561296,
          "lp_acc": 0.47127819061279297,
          "lp_f1": 0.33715210564009124
        },
        "test_cross_user": {
          "knn_acc": 0.4608968496322632,
          "knn_f1": 0.414296057929862,
          "lp_acc": 0.503096878528595,
          "lp_f1": 0.3505309015171454
        }
      },
      "layer_3": {
        "test_id": {
          "knn_acc": 0.9439374208450317,
          "knn_f1": 0.9436724716329054,
          "lp_acc": 0.5397652983665466,
          "lp_f1": 0.41429210540329536
        },
        "test_cross_device": {
          "knn_acc": 0.2992420196533203,
          "knn_f1": 0.2911457237861579,
          "lp_acc": 0.5174955725669861,
          "lp_f1": 0.37955087612800564
        },
        "test_cross_env": {
          "knn_acc": 0.3796992599964142,
          "knn_f1": 0.35797714219365034,
          "lp_acc": 0.47127819061279297,
          "lp_f1": 0.3514429497975765
        },
        "test_cross_user": {
          "knn_acc": 0.4509868621826172,
          "knn_f1": 0.403474433211065,
          "lp_acc": 0.4965727925300598,
          "lp_f1": 0.3510388737483982
        }
      },
      "layer_6": {
        "test_id": {
          "knn_acc": 0.9485006332397461,
          "knn_f1": 0.9482235778177323,
          "lp_acc": 0.5506301522254944,
          "lp_f1": 0.44167423007816065
        },
        "test_cross_device": {
          "knn_acc": 0.24317309260368347,
          "knn_f1": 0.2576454427980499,
          "lp_acc": 0.45395079255104065,
          "lp_f1": 0.3435747695434407
        },
        "test_cross_env": {
          "knn_acc": 0.3753383457660675,
          "knn_f1": 0.34983755971619623,
          "lp_acc": 0.4684210419654846,
          "lp_f1": 0.3564574858979474
        },
        "test_cross_user": {
          "knn_acc": 0.43504831194877625,
          "knn_f1": 0.39819321500858257,
          "lp_acc": 0.47989100217819214,
          "lp_f1": 0.356369032049501
        }
      },
      "layer_9": {
        "test_id": {
          "knn_acc": 0.9504563212394714,
          "knn_f1": 0.9501698036449359,
          "lp_acc": 0.5508474707603455,
          "lp_f1": 0.4438562880643035
        },
        "test_cross_device": {
          "knn_acc": 0.3028761148452759,
          "knn_f1": 0.3011850702506782,
          "lp_acc": 0.3596718907356262,
          "lp_f1": 0.3099870166720989
        },
        "test_cross_env": {
          "knn_acc": 0.3897744417190552,
          "knn_f1": 0.3616978983425468,
          "lp_acc": 0.4081203043460846,
          "lp_f1": 0.34159902945478743
        },
        "test_cross_user": {
          "knn_acc": 0.4383516311645508,
          "knn_f1": 0.3836412748759333,
          "lp_acc": 0.3742670714855194,
          "lp_f1": 0.3098703079288883
        }
      },
      "layer_12": {
        "test_id": {
          "knn_acc": 0.9493698477745056,
          "knn_f1": 0.9491013023535662,
          "lp_acc": 0.5447631478309631,
          "lp_f1": 0.43279545599303193
        },
        "test_cross_device": {
          "knn_acc": 0.31917765736579895,
          "knn_f1": 0.317691570780305,
          "lp_acc": 0.41646766662597656,
          "lp_f1": 0.32918079966428443
        },
        "test_cross_env": {
          "knn_acc": 0.3732330799102783,
          "knn_f1": 0.34218200031424156,
          "lp_acc": 0.5060150623321533,
          "lp_f1": 0.3469991640746941
        },
        "test_cross_user": {
          "knn_acc": 0.4512346088886261,
          "knn_f1": 0.3852566177330632,
          "lp_acc": 0.4113469421863556,
          "lp_f1": 0.32186640545860024
        }
      }
    },
    "epoch_100": {
      "layer_1": {
        "test_id": {
          "knn_acc": 0.9313341975212097,
          "knn_f1": 0.9307730045224745,
          "lp_acc": 0.5197740197181702,
          "lp_f1": 0.38081926723821463
        },
        "test_cross_device": {
          "knn_acc": 0.234035924077034,
          "knn_f1": 0.2517703861131473,
          "lp_acc": 0.5133423209190369,
          "lp_f1": 0.356164828188444
        },
        "test_cross_env": {
          "knn_acc": 0.4476691782474518,
          "knn_f1": 0.41297256651363495,
          "lp_acc": 0.4772932231426239,
          "lp_f1": 0.33980006611766944
        },
        "test_cross_user": {
          "knn_acc": 0.44768354296684265,
          "knn_f1": 0.40143137845556,
          "lp_acc": 0.5037575364112854,
          "lp_f1": 0.3491477113096452
        }
      },
      "layer_3": {
        "test_id": {
          "knn_acc": 0.9480660557746887,
          "knn_f1": 0.947851868758415,
          "lp_acc": 0.5391134023666382,
          "lp_f1": 0.4197035101909136
        },
        "test_cross_device": {
          "knn_acc": 0.24888381361961365,
          "knn_f1": 0.25856462795373236,
          "lp_acc": 0.5079430937767029,
          "lp_f1": 0.38290992708822175
        },
        "test_cross_env": {
          "knn_acc": 0.35639098286628723,
          "knn_f1": 0.34067104386605446,
          "lp_acc": 0.4708270728588104,
          "lp_f1": 0.36722826866356073
        },
        "test_cross_user": {
          "knn_acc": 0.4291849136352539,
          "knn_f1": 0.3777476744664637,
          "lp_acc": 0.49797672033309937,
          "lp_f1": 0.3587879807888148
        }
      },
      "layer_6": {
        "test_id": {
          "knn_acc": 0.9506736397743225,
          "knn_f1": 0.9504718903053264,
          "lp_acc": 0.5780095458030701,
          "lp_f1": 0.494274369603679
        },
        "test_cross_device": {
          "knn_acc": 0.2545945346355438,
          "knn_f1": 0.258747933154977,
          "lp_acc": 0.4387913942337036,
          "lp_f1": 0.3617738780243634
        },
        "test_cross_env": {
          "knn_acc": 0.3433082699775696,
          "knn_f1": 0.32355638513137724,
          "lp_acc": 0.425112783908844,
          "lp_f1": 0.3564662848919014
        },
        "test_cross_user": {
          "knn_acc": 0.4364522397518158,
          "knn_f1": 0.37825992983076917,
          "lp_acc": 0.4710545837879181,
          "lp_f1": 0.3573879948724553
        }
      },
      "layer_9": {
        "test_id": {
          "knn_acc": 0.9515427947044373,
          "knn_f1": 0.951282071116194,
          "lp_acc": 0.5714906454086304,
          "lp_f1": 0.4843244630340007
        },
        "test_cross_device": {
          "knn_acc": 0.34825044870376587,
          "knn_f1": 0.32213032614169307,
          "lp_acc": 0.32738032937049866,
          "lp_f1": 0.31347353802662115
        },
        "test_cross_env": {
          "knn_acc": 0.39293232560157776,
          "knn_f1": 0.3763753248306982,
          "lp_acc": 0.4218045175075531,
          "lp_f1": 0.3464526715492951
        },
        "test_cross_user": {
          "knn_acc": 0.4706416726112366,
          "knn_f1": 0.39540001777334827,
          "lp_acc": 0.40721777081489563,
          "lp_f1": 0.3398058848322902
        }
      },
      "layer_12": {
        "test_id": {
          "knn_acc": 0.9528465867042542,
          "knn_f1": 0.9526108341851641,
          "lp_acc": 0.558670163154602,
          "lp_f1": 0.4603678657320502
        },
        "test_cross_device": {
          "knn_acc": 0.3381787836551666,
          "knn_f1": 0.33285516668255793,
          "lp_acc": 0.3599833846092224,
          "lp_f1": 0.31108841924710406
        },
        "test_cross_env": {
          "knn_acc": 0.36556389927864075,
          "knn_f1": 0.339224028963701,
          "lp_acc": 0.4102255702018738,
          "lp_f1": 0.3344347963239855
        },
        "test_cross_user": {
          "knn_acc": 0.4711371660232544,
          "knn_f1": 0.3970239963759771,
          "lp_acc": 0.4260467290878296,
          "lp_f1": 0.3330342327597766
        }
      }
    },
    "epoch_150": {
      "layer_1": {
        "test_id": {
          "knn_acc": 0.9311168789863586,
          "knn_f1": 0.9305666620600784,
          "lp_acc": 0.5206431746482849,
          "lp_f1": 0.38420340352201326
        },
        "test_cross_device": {
          "knn_acc": 0.23289377987384796,
          "knn_f1": 0.25120785400604073,
          "lp_acc": 0.5070086121559143,
          "lp_f1": 0.343389485354099
        },
        "test_cross_env": {
          "knn_acc": 0.42812031507492065,
          "knn_f1": 0.40324262123048593,
          "lp_acc": 0.4703759253025055,
          "lp_f1": 0.33922818285424644
        },
        "test_cross_user": {
          "knn_acc": 0.4393426477909088,
          "knn_f1": 0.39612477421889064,
          "lp_acc": 0.5048311352729797,
          "lp_f1": 0.3513163539382614
        }
      },
      "layer_3": {
        "test_id": {
          "knn_acc": 0.9480660557746887,
          "knn_f1": 0.9478441775585287,
          "lp_acc": 0.5395480394363403,
          "lp_f1": 0.4234662498162271
        },
        "test_cross_device": {
          "knn_acc": 0.24410757422447205,
          "knn_f1": 0.2525326577883039,
          "lp_acc": 0.4893572926521301,
          "lp_f1": 0.36472923900190746
        },
        "test_cross_env": {
          "knn_acc": 0.3663157820701599,
          "knn_f1": 0.3427410569056468,
          "lp_acc": 0.47684210538864136,
          "lp_f1": 0.3657224225941845
        },
        "test_cross_user": {
          "knn_acc": 0.4234040677547455,
          "knn_f1": 0.3730379765262503,
          "lp_acc": 0.49954578280448914,
          "lp_f1": 0.36336195344487837
        }
      },
      "layer_6": {
        "test_id": {
          "knn_acc": 0.951325535774231,
          "knn_f1": 0.9510818684582043,
          "lp_acc": 0.582138180732727,
          "lp_f1": 0.5044365531067218
        },
        "test_cross_device": {
          "knn_acc": 0.26663896441459656,
          "knn_f1": 0.269646747316879,
          "lp_acc": 0.4316270351409912,
          "lp_f1": 0.3578147061431555
        },
        "test_cross_env": {
          "knn_acc": 0.32165414094924927,
          "knn_f1": 0.3093309155864821,
          "lp_acc": 0.39488720893859863,
          "lp_f1": 0.338143559325046
        },
        "test_cross_user": {
          "knn_acc": 0.4381864666938782,
          "knn_f1": 0.37817549827357794,
          "lp_acc": 0.47287142276763916,
          "lp_f1": 0.36557948308562
        }
      },
      "layer_9": {
        "test_id": {
          "knn_acc": 0.9519773721694946,
          "knn_f1": 0.9517583965147365,
          "lp_acc": 0.5814862847328186,
          "lp_f1": 0.5062897271956013
        },
        "test_cross_device": {
          "knn_acc": 0.37794622778892517,
          "knn_f1": 0.3498413154596313,
          "lp_acc": 0.30931368470191956,
          "lp_f1": 0.301471585341599
        },
        "test_cross_env": {
          "knn_acc": 0.39714285731315613,
          "knn_f1": 0.37875091172122227,
          "lp_acc": 0.3993985056877136,
          "lp_f1": 0.3564393292074378
        },
        "test_cross_user": {
          "knn_acc": 0.4766702353954315,
          "knn_f1": 0.39489249920550373,
          "lp_acc": 0.37319350242614746,
          "lp_f1": 0.31425886995270674
        }
      },
      "layer_12": {
        "test_id": {
          "knn_acc": 0.9526292681694031,
          "knn_f1": 0.9523652666426222,
          "lp_acc": 0.5673620104789734,
          "lp_f1": 0.4791658453848218
        },
        "test_cross_device": {
          "knn_acc": 0.3668362498283386,
          "knn_f1": 0.35352361285428197,
          "lp_acc": 0.33454468846321106,
          "lp_f1": 0.308346568827919
        },
        "test_cross_env": {
          "knn_acc": 0.3604511320590973,
          "knn_f1": 0.3387330734360316,
          "lp_acc": 0.4034586548805237,
          "lp_f1": 0.347074377242759
        },
        "test_cross_user": {
          "knn_acc": 0.48063424229621887,
          "knn_f1": 0.4030863838372327,
          "lp_acc": 0.4408291280269623,
          "lp_f1": 0.3426534057008896
        }
      }
    },
    "epoch_200": {
      "layer_1": {
        "test_id": {
          "knn_acc": 0.9306823015213013,
          "knn_f1": 0.9301688172980052,
          "lp_acc": 0.5189048051834106,
          "lp_f1": 0.38128425595653753
        },
        "test_cross_device": {
          "knn_acc": 0.23413975536823273,
          "knn_f1": 0.25331506831062867,
          "lp_acc": 0.5068009495735168,
          "lp_f1": 0.3434287128796272
        },
        "test_cross_env": {
          "knn_acc": 0.42120301723480225,
          "knn_f1": 0.3978601664590697,
          "lp_acc": 0.47022557258605957,
          "lp_f1": 0.33870615179164276
        },
        "test_cross_user": {
          "knn_acc": 0.43744322657585144,
          "knn_f1": 0.394135257400672,
          "lp_acc": 0.5081344246864319,
          "lp_f1": 0.35878098457543234
        }
      },
      "layer_3": {
        "test_id": {
          "knn_acc": 0.9485006332397461,
          "knn_f1": 0.9482811668567912,
          "lp_acc": 0.5391134023666382,
          "lp_f1": 0.4234569984547581
        },
        "test_cross_device": {
          "knn_acc": 0.2364240437746048,
          "knn_f1": 0.2477215940799632,
          "lp_acc": 0.49184924364089966,
          "lp_f1": 0.3717941496368802
        },
        "test_cross_env": {
          "knn_acc": 0.36902254819869995,
          "knn_f1": 0.34360971074736646,
          "lp_acc": 0.47879698872566223,
          "lp_f1": 0.3698283307090197
        },
        "test_cross_user": {
          "knn_acc": 0.4170451760292053,
          "knn_f1": 0.3688101949069392,
          "lp_acc": 0.49459078907966614,
          "lp_f1": 0.3611207229532491
        }
      },
      "layer_6": {
        "test_id": {
          "knn_acc": 0.954150378704071,
          "knn_f1": 0.9539076649422458,
          "lp_acc": 0.586266815662384,
          "lp_f1": 0.5108538184496512
        },
        "test_cross_device": {
          "knn_acc": 0.2562558352947235,
          "knn_f1": 0.2634790557116557,
          "lp_acc": 0.4086802899837494,
          "lp_f1": 0.35048419994844215
        },
        "test_cross_env": {
          "knn_acc": 0.3347368538379669,
          "knn_f1": 0.3154301290667225,
          "lp_acc": 0.40436089038848877,
          "lp_f1": 0.34533014369590276
        },
        "test_cross_user": {
          "knn_acc": 0.43240565061569214,
          "knn_f1": 0.3759590880640134,
          "lp_acc": 0.46973326802253723,
          "lp_f1": 0.36846003485019363
        }
      },
      "layer_9": {
        "test_id": {
          "knn_acc": 0.9530639052391052,
          "knn_f1": 0.9528217653555298,
          "lp_acc": 0.5832247138023376,
          "lp_f1": 0.5097628019902259
        },
        "test_cross_device": {
          "knn_acc": 0.37586960196495056,
          "knn_f1": 0.35444752761891685,
          "lp_acc": 0.31139031052589417,
          "lp_f1": 0.29441651434568283
        },
        "test_cross_env": {
          "knn_acc": 0.39624059200286865,
          "knn_f1": 0.3768742940716307,
          "lp_acc": 0.4117293357849121,
          "lp_f1": 0.3705572193886091
        },
        "test_cross_user": {
          "knn_acc": 0.4756792485713959,
          "knn_f1": 0.3992374866247561,
          "lp_acc": 0.3693946599960327,
          "lp_f1": 0.3152558800843012
        }
      },
      "layer_12": {
        "test_id": {
          "knn_acc": 0.9534984827041626,
          "knn_f1": 0.9532570636994644,
          "lp_acc": 0.5699695944786072,
          "lp_f1": 0.4871104230439352
        },
        "test_cross_device": {
          "knn_acc": 0.3622676730155945,
          "knn_f1": 0.3533955612948927,
          "lp_acc": 0.311078816652298,
          "lp_f1": 0.29119950632802033
        },
        "test_cross_env": {
          "knn_acc": 0.36090224981307983,
          "knn_f1": 0.335613981429693,
          "lp_acc": 0.41308271884918213,
          "lp_f1": 0.35828055141550197
        },
        "test_cross_user": {
          "knn_acc": 0.48013874888420105,
          "knn_f1": 0.4098657818351222,
          "lp_acc": 0.425881564617157,
          "lp_f1": 0.3297523540645144
        }
      }
    },
    "epoch_250": {
      "layer_1": {
        "test_id": {
          "knn_acc": 0.9311168789863586,
          "knn_f1": 0.9306426222498094,
          "lp_acc": 0.5199912786483765,
          "lp_f1": 0.38333354924216145
        },
        "test_cross_device": {
          "knn_acc": 0.23206312954425812,
          "knn_f1": 0.25304157433191615,
          "lp_acc": 0.5061779618263245,
          "lp_f1": 0.34327681421483835
        },
        "test_cross_env": {
          "knn_acc": 0.4198496341705322,
          "knn_f1": 0.3952255050115241,
          "lp_acc": 0.47218045592308044,
          "lp_f1": 0.33840431201136606
        },
        "test_cross_user": {
          "knn_acc": 0.43992072343826294,
          "knn_f1": 0.39741722470392504,
          "lp_acc": 0.5007019639015198,
          "lp_f1": 0.3461430728131573
        }
      },
      "layer_3": {
        "test_id": {
          "knn_acc": 0.9500217437744141,
          "knn_f1": 0.9498178102558303,
          "lp_acc": 0.5380269289016724,
          "lp_f1": 0.42146512463215347
        },
        "test_cross_device": {
          "knn_acc": 0.2419271171092987,
          "knn_f1": 0.2533613703429766,
          "lp_acc": 0.4923684000968933,
          "lp_f1": 0.3687480187985551
        },
        "test_cross_env": {
          "knn_acc": 0.37022557854652405,
          "knn_f1": 0.3430764683164761,
          "lp_acc": 0.4884210526943207,
          "lp_f1": 0.3716144476813178
        },
        "test_cross_user": {
          "knn_acc": 0.4185316562652588,
          "knn_f1": 0.37011615132846404,
          "lp_acc": 0.49293914437294006,
          "lp_f1": 0.36134637233266426
        }
      },
      "layer_6": {
        "test_id": {
          "knn_acc": 0.9532811641693115,
          "knn_f1": 0.9530025355470612,
          "lp_acc": 0.5847457647323608,
          "lp_f1": 0.5093914419528953
        },
        "test_cross_device": {
          "knn_acc": 0.2636278569698334,
          "knn_f1": 0.27390256560300286,
          "lp_acc": 0.4165714979171753,
          "lp_f1": 0.35450765464251716
        },
        "test_cross_env": {
          "knn_acc": 0.34285715222358704,
          "knn_f1": 0.3209070876138936,
          "lp_acc": 0.3957894742488861,
          "lp_f1": 0.3370697887542987
        },
        "test_cross_user": {
          "knn_acc": 0.43504831194877625,
          "knn_f1": 0.37840666360478253,
          "lp_acc": 0.4690725803375244,
          "lp_f1": 0.36851946086675585
        }
      },
      "layer_9": {
        "test_id": {
          "knn_acc": 0.9532811641693115,
          "knn_f1": 0.953063079843216,
          "lp_acc": 0.5840938687324524,
          "lp_f1": 0.5114321556950134
        },
        "test_cross_device": {
          "knn_acc": 0.37202781438827515,
          "knn_f1": 0.3531258915539915,
          "lp_acc": 0.31959298253059387,
          "lp_f1": 0.297674824923838
        },
        "test_cross_env": {
          "knn_acc": 0.3926315903663635,
          "knn_f1": 0.37434267753450035,
          "lp_acc": 0.41007518768310547,
          "lp_f1": 0.36864228153751283
        },
        "test_cross_user": {
          "knn_acc": 0.47477084398269653,
          "knn_f1": 0.3964425111382734,
          "lp_acc": 0.36468741297721863,
          "lp_f1": 0.30357436153446365
        }
      },
      "layer_12": {
        "test_id": {
          "knn_acc": 0.9532811641693115,
          "knn_f1": 0.9530585455587948,
          "lp_acc": 0.5701868534088135,
          "lp_f1": 0.48611796986746625
        },
        "test_cross_device": {
          "knn_acc": 0.3552071452140808,
          "knn_f1": 0.347547272747301,
          "lp_acc": 0.33205273747444153,
          "lp_f1": 0.3052499649172685
        },
        "test_cross_env": {
          "knn_acc": 0.36345863342285156,
          "knn_f1": 0.33647728943448973,
          "lp_acc": 0.4240601360797882,
          "lp_f1": 0.3635679588501837
        },
        "test_cross_user": {
          "knn_acc": 0.47526633739471436,
          "knn_f1": 0.4047101248567877,
          "lp_acc": 0.4321579039096832,
          "lp_f1": 0.33673974567477616
        }
      }
    },
    "epoch_300": {
      "layer_1": {
        "test_id": {
          "knn_acc": 0.9315515160560608,
          "knn_f1": 0.9310975261724413,
          "lp_acc": 0.5204259157180786,
          "lp_f1": 0.3831561957640654
        },
        "test_cross_device": {
          "knn_acc": 0.22728689014911652,
          "knn_f1": 0.2486003595013942,
          "lp_acc": 0.5072162747383118,
          "lp_f1": 0.343259090957793
        },
        "test_cross_env": {
          "knn_acc": 0.41909775137901306,
          "knn_f1": 0.3947496993353052,
          "lp_acc": 0.46631577610969543,
          "lp_f1": 0.3362148618243363
        },
        "test_cross_user": {
          "knn_acc": 0.43744322657585144,
          "knn_f1": 0.39560574646652036,
          "lp_acc": 0.5029317140579224,
          "lp_f1": 0.34756886397883807
        }
      },
      "layer_3": {
        "test_id": {
          "knn_acc": 0.9504563212394714,
          "knn_f1": 0.9502220064578317,
          "lp_acc": 0.5395480394363403,
          "lp_f1": 0.423641744536498
        },
        "test_cross_device": {
          "knn_acc": 0.23569722473621368,
          "knn_f1": 0.24822959719147286,
          "lp_acc": 0.49423736333847046,
          "lp_f1": 0.37584871553292765
        },
        "test_cross_env": {
          "knn_acc": 0.3687218129634857,
          "knn_f1": 0.3415596817644923,
          "lp_acc": 0.48721805214881897,
          "lp_f1": 0.37067850220697657
        },
        "test_cross_user": {
          "knn_acc": 0.4160541892051697,
          "knn_f1": 0.36963226787422426,
          "lp_acc": 0.49244365096092224,
          "lp_f1": 0.36070299405442596
        }
      },
      "layer_6": {
        "test_id": {
          "knn_acc": 0.9534984827041626,
          "knn_f1": 0.9532184520313313,
          "lp_acc": 0.5869187116622925,
          "lp_f1": 0.5128037310939731
        },
        "test_cross_device": {
          "knn_acc": 0.26144739985466003,
          "knn_f1": 0.27253036233117656,
          "lp_acc": 0.41169142723083496,
          "lp_f1": 0.3519088460487363
        },
        "test_cross_env": {
          "knn_acc": 0.34541353583335876,
          "knn_f1": 0.3223303012896569,
          "lp_acc": 0.40330827236175537,
          "lp_f1": 0.3410776124960492
        },
        "test_cross_user": {
          "knn_acc": 0.4317449927330017,
          "knn_f1": 0.37597210370892936,
          "lp_acc": 0.47534891963005066,
          "lp_f1": 0.3781015538046827
        }
      },
      "layer_9": {
        "test_id": {
          "knn_acc": 0.9528465867042542,
          "knn_f1": 0.9526162411484936,
          "lp_acc": 0.5843111872673035,
          "lp_f1": 0.5115099375060267
        },
        "test_cross_device": {
          "knn_acc": 0.3698473572731018,
          "knn_f1": 0.35231661378317297,
          "lp_acc": 0.31575122475624084,
          "lp_f1": 0.29712170996204285
        },
        "test_cross_env": {
          "knn_acc": 0.39533835649490356,
          "knn_f1": 0.37493659077541375,
          "lp_acc": 0.41864660382270813,
          "lp_f1": 0.3723614304192876
        },
        "test_cross_user": {
          "knn_acc": 0.4740275740623474,
          "knn_f1": 0.3952423651313398,
          "lp_acc": 0.36485257744789124,
          "lp_f1": 0.3026244357030896
        }
      },
      "layer_12": {
        "test_id": {
          "knn_acc": 0.9537158012390137,
          "knn_f1": 0.953479672625455,
          "lp_acc": 0.5693176984786987,
          "lp_f1": 0.485736539326059
        },
        "test_cross_device": {
          "knn_acc": 0.3534420132637024,
          "knn_f1": 0.346688598578792,
          "lp_acc": 0.31481674313545227,
          "lp_f1": 0.2954628283288568
        },
        "test_cross_env": {
          "knn_acc": 0.36330828070640564,
          "knn_f1": 0.3355902771356604,
          "lp_acc": 0.42255640029907227,
          "lp_f1": 0.36439507739126786
        },
        "test_cross_user": {
          "knn_acc": 0.4735320806503296,
          "knn_f1": 0.40260485776554794,
          "lp_acc": 0.43521347641944885,
          "lp_f1": 0.33665271560797083
        }
      }
    }
  }
}