{
  "exp": "mae_har_ep300_mask0.75_strategymixed_ph29pw25_seed42_enc12_dim128_bs128",
  "args": {
    "epochs": 300,
    "mask_ratio": 0.75,
    "encoder_depth": 12,
    "encoder_dim": 128,
    "decoder_dim": 64,
    "batch_size": 128,
    "lr": 0.00015,
    "eval_layers": "1,3,6",
    "eval_every": 50,
    "mask_strategy": "mixed",
    "patch_h": 29,
    "patch_w": 25,
    "seed": 42,
    "skip_mem_check": false,
    "mem_budget_gb": 20.0,
    "padded_h": 232,
    "padded_w": 500,
    "num_patches": 160
  },
  "loss_log": [
    {
      "epoch": 1,
      "loss": 0.9680244397549402
    },
    {
      "epoch": 2,
      "loss": 0.5093804008903957
    },
    {
      "epoch": 3,
      "loss": 0.44080195682389395
    },
    {
      "epoch": 4,
      "loss": 0.41555467283441905
    },
    {
      "epoch": 5,
      "loss": 0.3954697599013646
    },
    {
      "epoch": 6,
      "loss": 0.3774955799537046
    },
    {
      "epoch": 7,
      "loss": 0.35309880617119016
    },
    {
      "epoch": 8,
      "loss": 0.33209012023040224
    },
    {
      "epoch": 9,
      "loss": 0.3173125960997173
    },
    {
      "epoch": 10,
      "loss": 0.3028877024494466
    },
    {
      "epoch": 11,
      "loss": 0.29358114603729474
    },
    {
      "epoch": 12,
      "loss": 0.28191335561374825
    },
    {
      "epoch": 13,
      "loss": 0.2714578527070227
    },
    {
      "epoch": 14,
      "loss": 0.261300121567079
    },
    {
      "epoch": 15,
      "loss": 0.2532044676620336
    },
    {
      "epoch": 16,
      "loss": 0.2500139029607886
    },
    {
      "epoch": 17,
      "loss": 0.2423251478799752
    },
    {
      "epoch": 18,
      "loss": 0.23628902364344823
    },
    {
      "epoch": 19,
      "loss": 0.2312786372467166
    },
    {
      "epoch": 20,
      "loss": 0.22599697698439872
    },
    {
      "epoch": 21,
      "loss": 0.22363569179461115
    },
    {
      "epoch": 22,
      "loss": 0.2212577782393921
    },
    {
      "epoch": 23,
      "loss": 0.2185929026454687
    },
    {
      "epoch": 24,
      "loss": 0.21605559092547214
    },
    {
      "epoch": 25,
      "loss": 0.21479464331198306
    },
    {
      "epoch": 26,
      "loss": 0.21358039797771544
    },
    {
      "epoch": 27,
      "loss": 0.2121054401532525
    },
    {
      "epoch": 28,
      "loss": 0.21120902904797167
    },
    {
      "epoch": 29,
      "loss": 0.20962237593318736
    },
    {
      "epoch": 30,
      "loss": 0.20938274769910745
    },
    {
      "epoch": 31,
      "loss": 0.20732221752405167
    },
    {
      "epoch": 32,
      "loss": 0.20643539416293302
    },
    {
      "epoch": 33,
      "loss": 0.20626044592687062
    },
    {
      "epoch": 34,
      "loss": 0.20752789656675996
    },
    {
      "epoch": 35,
      "loss": 0.20376526449053062
    },
    {
      "epoch": 36,
      "loss": 0.20358950077068239
    },
    {
      "epoch": 37,
      "loss": 0.20326543501800015
    },
    {
      "epoch": 38,
      "loss": 0.20223705071423734
    },
    {
      "epoch": 39,
      "loss": 0.20214938549768358
    },
    {
      "epoch": 40,
      "loss": 0.20036216692200728
    },
    {
      "epoch": 41,
      "loss": 0.19948353112808295
    },
    {
      "epoch": 42,
      "loss": 0.19900503390956492
    },
    {
      "epoch": 43,
      "loss": 0.19824885293131783
    },
    {
      "epoch": 44,
      "loss": 0.19655897468328476
    },
    {
      "epoch": 45,
      "loss": 0.19601404658030896
    },
    {
      "epoch": 46,
      "loss": 0.19424785913101264
    },
    {
      "epoch": 47,
      "loss": 0.19600865129558814
    },
    {
      "epoch": 48,
      "loss": 0.19520131968671367
    },
    {
      "epoch": 49,
      "loss": 0.19382170197509585
    },
    {
      "epoch": 50,
      "loss": 0.19248002909478687
    },
    {
      "epoch": 51,
      "loss": 0.19318232871592045
    },
    {
      "epoch": 52,
      "loss": 0.19191875690150828
    },
    {
      "epoch": 53,
      "loss": 0.19144415270004952
    },
    {
      "epoch": 54,
      "loss": 0.19405555955710865
    },
    {
      "epoch": 55,
      "loss": 0.1915775171170632
    },
    {
      "epoch": 56,
      "loss": 0.19109101655582586
    },
    {
      "epoch": 57,
      "loss": 0.18979082895176752
    },
    {
      "epoch": 58,
      "loss": 0.18870636927230017
    },
    {
      "epoch": 59,
      "loss": 0.18903258194526038
    },
    {
      "epoch": 60,
      "loss": 0.18872937533472264
    },
    {
      "epoch": 61,
      "loss": 0.18908118607387656
    },
    {
      "epoch": 62,
      "loss": 0.18855796541486466
    },
    {
      "epoch": 63,
      "loss": 0.18919689474361284
    },
    {
      "epoch": 64,
      "loss": 0.1879162516977106
    },
    {
      "epoch": 65,
      "loss": 0.1876272423458951
    },
    {
      "epoch": 66,
      "loss": 0.18903803275454611
    },
    {
      "epoch": 67,
      "loss": 0.18841776633191676
    },
    {
      "epoch": 68,
      "loss": 0.18690787273503484
    },
    {
      "epoch": 69,
      "loss": 0.18774514973518394
    },
    {
      "epoch": 70,
      "loss": 0.18801898367348172
    },
    {
      "epoch": 71,
      "loss": 0.1858360397496394
    },
    {
      "epoch": 72,
      "loss": 0.18731561808713845
    },
    {
      "epoch": 73,
      "loss": 0.18694300009381204
    },
    {
      "epoch": 74,
      "loss": 0.18642810767605192
    },
    {
      "epoch": 75,
      "loss": 0.1870912446507386
    },
    {
      "epoch": 76,
      "loss": 0.18703677762477172
    },
    {
      "epoch": 77,
      "loss": 0.1862736658326217
    },
    {
      "epoch": 78,
      "loss": 0.1851190154751142
    },
    {
      "epoch": 79,
      "loss": 0.18628081856738954
    },
    {
      "epoch": 80,
      "loss": 0.1856618109380915
    },
    {
      "epoch": 81,
      "loss": 0.18610206556816897
    },
    {
      "epoch": 82,
      "loss": 0.18567649283934207
    },
    {
      "epoch": 83,
      "loss": 0.18533608769731863
    },
    {
      "epoch": 84,
      "loss": 0.18458756077147664
    },
    {
      "epoch": 85,
      "loss": 0.18475477087001005
    },
    {
      "epoch": 86,
      "loss": 0.18499452913446085
    },
    {
      "epoch": 87,
      "loss": 0.1842651523294903
    },
    {
      "epoch": 88,
      "loss": 0.1851497252604791
    },
    {
      "epoch": 89,
      "loss": 0.1846196703790199
    },
    {
      "epoch": 90,
      "loss": 0.184492398585592
    },
    {
      "epoch": 91,
      "loss": 0.18449090669552484
    },
    {
      "epoch": 92,
      "loss": 0.18426344162296682
    },
    {
      "epoch": 93,
      "loss": 0.18511067632408368
    },
    {
      "epoch": 94,
      "loss": 0.18330697360492887
    },
    {
      "epoch": 95,
      "loss": 0.1837864106609708
    },
    {
      "epoch": 96,
      "loss": 0.18434138853280319
    },
    {
      "epoch": 97,
      "loss": 0.1839255867969422
    },
    {
      "epoch": 98,
      "loss": 0.18318569615838073
    },
    {
      "epoch": 99,
      "loss": 0.18401971308603174
    },
    {
      "epoch": 100,
      "loss": 0.18445218354463577
    },
    {
      "epoch": 101,
      "loss": 0.1826139749693019
    },
    {
      "epoch": 102,
      "loss": 0.18330422691291287
    },
    {
      "epoch": 103,
      "loss": 0.18327209530841737
    },
    {
      "epoch": 104,
      "loss": 0.1836366563858021
    },
    {
      "epoch": 105,
      "loss": 0.18336747045673074
    },
    {
      "epoch": 106,
      "loss": 0.18297897962232432
    },
    {
      "epoch": 107,
      "loss": 0.18395415116988478
    },
    {
      "epoch": 108,
      "loss": 0.18254540869522662
    },
    {
      "epoch": 109,
      "loss": 0.1825456710621005
    },
    {
      "epoch": 110,
      "loss": 0.18330899510710014
    },
    {
      "epoch": 111,
      "loss": 0.18260320754987852
    },
    {
      "epoch": 112,
      "loss": 0.18081887829161825
    },
    {
      "epoch": 113,
      "loss": 0.18276889985870748
    },
    {
      "epoch": 114,
      "loss": 0.18213631957769394
    },
    {
      "epoch": 115,
      "loss": 0.1819992476985568
    },
    {
      "epoch": 116,
      "loss": 0.18300697163102173
    },
    {
      "epoch": 117,
      "loss": 0.18210025717105185
    },
    {
      "epoch": 118,
      "loss": 0.18267646573838733
    },
    {
      "epoch": 119,
      "loss": 0.18227461211028553
    },
    {
      "epoch": 120,
      "loss": 0.18163343226271017
    },
    {
      "epoch": 121,
      "loss": 0.1813685835472175
    },
    {
      "epoch": 122,
      "loss": 0.18207348217921598
    },
    {
      "epoch": 123,
      "loss": 0.18070292863107862
    },
    {
      "epoch": 124,
      "loss": 0.18139560804480598
    },
    {
      "epoch": 125,
      "loss": 0.18154455437546685
    },
    {
      "epoch": 126,
      "loss": 0.18110527089309125
    },
    {
      "epoch": 127,
      "loss": 0.18201185088782085
    },
    {
      "epoch": 128,
      "loss": 0.18048057013324328
    },
    {
      "epoch": 129,
      "loss": 0.18146073019930295
    },
    {
      "epoch": 130,
      "loss": 0.18129793270712807
    },
    {
      "epoch": 131,
      "loss": 0.18167263047680968
    },
    {
      "epoch": 132,
      "loss": 0.18102809236872763
    },
    {
      "epoch": 133,
      "loss": 0.1809317417265404
    },
    {
      "epoch": 134,
      "loss": 0.18030028133874848
    },
    {
      "epoch": 135,
      "loss": 0.18006725289991923
    },
    {
      "epoch": 136,
      "loss": 0.18017808108457498
    },
    {
      "epoch": 137,
      "loss": 0.18079874345234462
    },
    {
      "epoch": 138,
      "loss": 0.18079229151563986
    },
    {
      "epoch": 139,
      "loss": 0.18093888319673992
    },
    {
      "epoch": 140,
      "loss": 0.18051088840833732
    },
    {
      "epoch": 141,
      "loss": 0.18100546424587569
    },
    {
      "epoch": 142,
      "loss": 0.18019702409704527
    },
    {
      "epoch": 143,
      "loss": 0.18085096962749958
    },
    {
      "epoch": 144,
      "loss": 0.17851427126498448
    },
    {
      "epoch": 145,
      "loss": 0.1813301726998318
    },
    {
      "epoch": 146,
      "loss": 0.1805902687566621
    },
    {
      "epoch": 147,
      "loss": 0.180937924377975
    },
    {
      "epoch": 148,
      "loss": 0.1796245470288254
    },
    {
      "epoch": 149,
      "loss": 0.18050775366524854
    },
    {
      "epoch": 150,
      "loss": 0.1804472775686355
    },
    {
      "epoch": 151,
      "loss": 0.17960244842938014
    },
    {
      "epoch": 152,
      "loss": 0.17986195791690124
    },
    {
      "epoch": 153,
      "loss": 0.18063231406822092
    },
    {
      "epoch": 154,
      "loss": 0.18057631639142832
    },
    {
      "epoch": 155,
      "loss": 0.17816408528458505
    },
    {
      "epoch": 156,
      "loss": 0.179868721624925
    },
    {
      "epoch": 157,
      "loss": 0.1788937028142668
    },
    {
      "epoch": 158,
      "loss": 0.17977490967937879
    },
    {
      "epoch": 159,
      "loss": 0.18053950325009369
    },
    {
      "epoch": 160,
      "loss": 0.17819017739523024
    },
    {
      "epoch": 161,
      "loss": 0.17910712026059628
    },
    {
      "epoch": 162,
      "loss": 0.17982962931550683
    },
    {
      "epoch": 163,
      "loss": 0.17922620120502653
    },
    {
      "epoch": 164,
      "loss": 0.17944451031230746
    },
    {
      "epoch": 165,
      "loss": 0.1781963553457033
    },
    {
      "epoch": 166,
      "loss": 0.1796028752412115
    },
    {
      "epoch": 167,
      "loss": 0.17771349767489092
    },
    {
      "epoch": 168,
      "loss": 0.1791574734130076
    },
    {
      "epoch": 169,
      "loss": 0.17927121397640025
    },
    {
      "epoch": 170,
      "loss": 0.17810937416340625
    },
    {
      "epoch": 171,
      "loss": 0.17920354806951114
    },
    {
      "epoch": 172,
      "loss": 0.1791708790475414
    },
    {
      "epoch": 173,
      "loss": 0.17907590312617166
    },
    {
      "epoch": 174,
      "loss": 0.17844203309643836
    },
    {
      "epoch": 175,
      "loss": 0.17993890094969953
    },
    {
      "epoch": 176,
      "loss": 0.1784469930543786
    },
    {
      "epoch": 177,
      "loss": 0.1785590782584179
    },
    {
      "epoch": 178,
      "loss": 0.1784618624619075
    },
    {
      "epoch": 179,
      "loss": 0.1794550364748353
    },
    {
      "epoch": 180,
      "loss": 0.1783855546798025
    },
    {
      "epoch": 181,
      "loss": 0.17887159383722714
    },
    {
      "epoch": 182,
      "loss": 0.17831258333864666
    },
    {
      "epoch": 183,
      "loss": 0.17903481503682478
    },
    {
      "epoch": 184,
      "loss": 0.17880070280461086
    },
    {
      "epoch": 185,
      "loss": 0.17883160062843845
    },
    {
      "epoch": 186,
      "loss": 0.17741998551147325
    },
    {
      "epoch": 187,
      "loss": 0.17758944080699057
    },
    {
      "epoch": 188,
      "loss": 0.17927382868670283
    },
    {
      "epoch": 189,
      "loss": 0.17843272936131274
    },
    {
      "epoch": 190,
      "loss": 0.17783798924869015
    },
    {
      "epoch": 191,
      "loss": 0.17768124020880177
    },
    {
      "epoch": 192,
      "loss": 0.1782461138708251
    },
    {
      "epoch": 193,
      "loss": 0.1780414618551731
    },
    {
      "epoch": 194,
      "loss": 0.177311318083888
    },
    {
      "epoch": 195,
      "loss": 0.17716809459740207
    },
    {
      "epoch": 196,
      "loss": 0.1776747154515414
    },
    {
      "epoch": 197,
      "loss": 0.17820120824589616
    },
    {
      "epoch": 198,
      "loss": 0.17846874976974159
    },
    {
      "epoch": 199,
      "loss": 0.17728639704485735
    },
    {
      "epoch": 200,
      "loss": 0.1783532558807305
    },
    {
      "epoch": 201,
      "loss": 0.177915653302556
    },
    {
      "epoch": 202,
      "loss": 0.1768166400669586
    },
    {
      "epoch": 203,
      "loss": 0.17734495062558425
    },
    {
      "epoch": 204,
      "loss": 0.1768354626283759
    },
    {
      "epoch": 205,
      "loss": 0.17792266154927866
    },
    {
      "epoch": 206,
      "loss": 0.1778273700426022
    },
    {
      "epoch": 207,
      "loss": 0.17780249663406894
    },
    {
      "epoch": 208,
      "loss": 0.1772543022497779
    },
    {
      "epoch": 209,
      "loss": 0.17770192736671084
    },
    {
      "epoch": 210,
      "loss": 0.17795126140117645
    },
    {
      "epoch": 211,
      "loss": 0.17685132855105967
    },
    {
      "epoch": 212,
      "loss": 0.1781590666089739
    },
    {
      "epoch": 213,
      "loss": 0.17654083048303923
    },
    {
      "epoch": 214,
      "loss": 0.17808618848877295
    },
    {
      "epoch": 215,
      "loss": 0.17725733295083046
    },
    {
      "epoch": 216,
      "loss": 0.1773647154193549
    },
    {
      "epoch": 217,
      "loss": 0.1782295676391749
    },
    {
      "epoch": 218,
      "loss": 0.1775918138169107
    },
    {
      "epoch": 219,
      "loss": 0.17612942095313752
    },
    {
      "epoch": 220,
      "loss": 0.17834313515396344
    },
    {
      "epoch": 221,
      "loss": 0.17683787333468595
    },
    {
      "epoch": 222,
      "loss": 0.17667005273203054
    },
    {
      "epoch": 223,
      "loss": 0.17709035000630788
    },
    {
      "epoch": 224,
      "loss": 0.177067028890763
    },
    {
      "epoch": 225,
      "loss": 0.17769850843719073
    },
    {
      "epoch": 226,
      "loss": 0.17668401591834568
    },
    {
      "epoch": 227,
      "loss": 0.17695131064170883
    },
    {
      "epoch": 228,
      "loss": 0.17736200030360902
    },
    {
      "epoch": 229,
      "loss": 0.1780074139436086
    },
    {
      "epoch": 230,
      "loss": 0.17758120463362762
    },
    {
      "epoch": 231,
      "loss": 0.1761899082256215
    },
    {
      "epoch": 232,
      "loss": 0.17726716310495422
    },
    {
      "epoch": 233,
      "loss": 0.17770218503262317
    },
    {
      "epoch": 234,
      "loss": 0.17676857060619763
    },
    {
      "epoch": 235,
      "loss": 0.17652958533948376
    },
    {
      "epoch": 236,
      "loss": 0.17666835036306155
    },
    {
      "epoch": 237,
      "loss": 0.1773290933952445
    },
    {
      "epoch": 238,
      "loss": 0.1760989690110797
    },
    {
      "epoch": 239,
      "loss": 0.17686080293995993
    },
    {
      "epoch": 240,
      "loss": 0.17688492277548426
    },
    {
      "epoch": 241,
      "loss": 0.17694718665665105
    },
    {
      "epoch": 242,
      "loss": 0.17748274308230197
    },
    {
      "epoch": 243,
      "loss": 0.1761190222487563
    },
    {
      "epoch": 244,
      "loss": 0.17712486100693545
    },
    {
      "epoch": 245,
      "loss": 0.1784185098395461
    },
    {
      "epoch": 246,
      "loss": 0.176050325678218
    },
    {
      "epoch": 247,
      "loss": 0.1766515744051763
    },
    {
      "epoch": 248,
      "loss": 0.1758497009674708
    },
    {
      "epoch": 249,
      "loss": 0.17638905399612018
    },
    {
      "epoch": 250,
      "loss": 0.17686185382661365
    },
    {
      "epoch": 251,
      "loss": 0.17654512778279327
    },
    {
      "epoch": 252,
      "loss": 0.17700249737217313
    },
    {
      "epoch": 253,
      "loss": 0.17651399012122834
    },
    {
      "epoch": 254,
      "loss": 0.17580978075663248
    },
    {
      "epoch": 255,
      "loss": 0.1753388519088427
    },
    {
      "epoch": 256,
      "loss": 0.17653390836148036
    },
    {
      "epoch": 257,
      "loss": 0.17661739974504426
    },
    {
      "epoch": 258,
      "loss": 0.17665825535853705
    },
    {
      "epoch": 259,
      "loss": 0.17681730538606644
    },
    {
      "epoch": 260,
      "loss": 0.1755326921563773
    },
    {
      "epoch": 261,
      "loss": 0.1762797754435312
    },
    {
      "epoch": 262,
      "loss": 0.17713242015313535
    },
    {
      "epoch": 263,
      "loss": 0.1756584340085586
    },
    {
      "epoch": 264,
      "loss": 0.17602170622419744
    },
    {
      "epoch": 265,
      "loss": 0.17664761628423417
    },
    {
      "epoch": 266,
      "loss": 0.17629464458496796
    },
    {
      "epoch": 267,
      "loss": 0.17581457786616825
    },
    {
      "epoch": 268,
      "loss": 0.17640124891130698
    },
    {
      "epoch": 269,
      "loss": 0.17653279148396991
    },
    {
      "epoch": 270,
      "loss": 0.17544108930797803
    },
    {
      "epoch": 271,
      "loss": 0.1771754368784882
    },
    {
      "epoch": 272,
      "loss": 0.17537221818098
    },
    {
      "epoch": 273,
      "loss": 0.1758049080769221
    },
    {
      "epoch": 274,
      "loss": 0.17693402272249972
    },
    {
      "epoch": 275,
      "loss": 0.1765934525146371
    },
    {
      "epoch": 276,
      "loss": 0.1765771952590772
    },
    {
      "epoch": 277,
      "loss": 0.17676971799560956
    },
    {
      "epoch": 278,
      "loss": 0.1759214001219897
    },
    {
      "epoch": 279,
      "loss": 0.17587493439870222
    },
    {
      "epoch": 280,
      "loss": 0.17671072970898377
    },
    {
      "epoch": 281,
      "loss": 0.17593731979529062
    },
    {
      "epoch": 282,
      "loss": 0.17529668845236301
    },
    {
      "epoch": 283,
      "loss": 0.17625557418380464
    },
    {
      "epoch": 284,
      "loss": 0.1751222409130562
    },
    {
      "epoch": 285,
      "loss": 0.17583312262736617
    },
    {
      "epoch": 286,
      "loss": 0.17589314618990534
    },
    {
      "epoch": 287,
      "loss": 0.1765473090289604
    },
    {
      "epoch": 288,
      "loss": 0.17517603295189993
    },
    {
      "epoch": 289,
      "loss": 0.1763373658593212
    },
    {
      "epoch": 290,
      "loss": 0.1758797433049906
    },
    {
      "epoch": 291,
      "loss": 0.17651996397901148
    },
    {
      "epoch": 292,
      "loss": 0.1768096767898117
    },
    {
      "epoch": 293,
      "loss": 0.17562001349315756
    },
    {
      "epoch": 294,
      "loss": 0.17634778061792963
    },
    {
      "epoch": 295,
      "loss": 0.1764316267910458
    },
    {
      "epoch": 296,
      "loss": 0.17626110694947697
    },
    {
      "epoch": 297,
      "loss": 0.17669063700096949
    },
    {
      "epoch": 298,
      "loss": 0.17576105528998942
    },
    {
      "epoch": 299,
      "loss": 0.17600813791865394
    },
    {
      "epoch": 300,
      "loss": 0.17566767157543273
    }
  ],
  "evals": {
    "epoch_50": {
      "layer_1": {
        "test_id": {
          "knn_acc": 0.9226423501968384,
          "knn_f1": 0.9220376153221772,
          "lp_acc": 0.5230334401130676,
          "lp_f1": 0.3874231328400303
        },
        "test_cross_device": {
          "knn_acc": 0.2713114023208618,
          "knn_f1": 0.28126935283375215,
          "lp_acc": 0.5109542012214661,
          "lp_f1": 0.366439352365308
        },
        "test_cross_env": {
          "knn_acc": 0.34406015276908875,
          "knn_f1": 0.32893697286758883,
          "lp_acc": 0.45759397745132446,
          "lp_f1": 0.351917690469352
        },
        "test_cross_user": {
          "knn_acc": 0.44776612520217896,
          "knn_f1": 0.4056124427730921,
          "lp_acc": 0.5016103982925415,
          "lp_f1": 0.35665538050078605
        }
      },
      "layer_3": {
        "test_id": {
          "knn_acc": 0.9389395713806152,
          "knn_f1": 0.9386528710912625,
          "lp_acc": 0.545849621295929,
          "lp_f1": 0.42286603144706686
        },
        "test_cross_device": {
          "knn_acc": 0.24836465716362,
          "knn_f1": 0.2619964475172454,
          "lp_acc": 0.4036963880062103,
          "lp_f1": 0.3294456357495806
        },
        "test_cross_env": {
          "knn_acc": 0.3300751745700836,
          "knn_f1": 0.3276815665654958,
          "lp_acc": 0.44270676374435425,
          "lp_f1": 0.3565944248514533
        },
        "test_cross_user": {
          "knn_acc": 0.4566025137901306,
          "knn_f1": 0.40027541529160815,
          "lp_acc": 0.4611445963382721,
          "lp_f1": 0.34033238639830166
        }
      },
      "layer_6": {
        "test_id": {
          "knn_acc": 0.9493698477745056,
          "knn_f1": 0.949109704082671,
          "lp_acc": 0.5564971566200256,
          "lp_f1": 0.45168355588322956
        },
        "test_cross_device": {
          "knn_acc": 0.3032914400100708,
          "knn_f1": 0.31133247219449556,
          "lp_acc": 0.2917661666870117,
          "lp_f1": 0.29501653972372777
        },
        "test_cross_env": {
          "knn_acc": 0.3664661645889282,
          "knn_f1": 0.3466092662466949,
          "lp_acc": 0.4781954884529114,
          "lp_f1": 0.38060307532761944
        },
        "test_cross_user": {
          "knn_acc": 0.4690725803375244,
          "knn_f1": 0.41826189323457175,
          "lp_acc": 0.4617226719856262,
          "lp_f1": 0.3498816916236038
        }
      }
    },
    "epoch_100": {
      "layer_1": {
        "test_id": {
          "knn_acc": 0.9222077131271362,
          "knn_f1": 0.9216282195092694,
          "lp_acc": 0.5245545506477356,
          "lp_f1": 0.39051254873842495
        },
        "test_cross_device": {
          "knn_acc": 0.3152320683002472,
          "knn_f1": 0.30963717606256963,
          "lp_acc": 0.49724847078323364,
          "lp_f1": 0.3704333409215506
        },
        "test_cross_env": {
          "knn_acc": 0.3381955027580261,
          "knn_f1": 0.3243882928960484,
          "lp_acc": 0.46631577610969543,
          "lp_f1": 0.355437763788658
        },
        "test_cross_user": {
          "knn_acc": 0.4667602479457855,
          "knn_f1": 0.4088819535574287,
          "lp_acc": 0.5015277862548828,
          "lp_f1": 0.3574091245189789
        }
      },
      "layer_3": {
        "test_id": {
          "knn_acc": 0.9387223124504089,
          "knn_f1": 0.9383460508177055,
          "lp_acc": 0.5517166256904602,
          "lp_f1": 0.43663877771462517
        },
        "test_cross_device": {
          "knn_acc": 0.2773336172103882,
          "knn_f1": 0.2919192509597177,
          "lp_acc": 0.43308067321777344,
          "lp_f1": 0.3424033942262658
        },
        "test_cross_env": {
          "knn_acc": 0.29518797993659973,
          "knn_f1": 0.30001779214598495,
          "lp_acc": 0.4396992623806,
          "lp_f1": 0.3466701699826534
        },
        "test_cross_user": {
          "knn_acc": 0.4609794318675995,
          "knn_f1": 0.40358835343159233,
          "lp_acc": 0.5065653920173645,
          "lp_f1": 0.3768503423524148
        }
      },
      "layer_6": {
        "test_id": {
          "knn_acc": 0.9495871067047119,
          "knn_f1": 0.9493459281211233,
          "lp_acc": 0.5621469020843506,
          "lp_f1": 0.4712259210378562
        },
        "test_cross_device": {
          "knn_acc": 0.2767106294631958,
          "knn_f1": 0.27190273491130046,
          "lp_acc": 0.35572630167007446,
          "lp_f1": 0.33782363913451846
        },
        "test_cross_env": {
          "knn_acc": 0.3264661729335785,
          "knn_f1": 0.30651408906782396,
          "lp_acc": 0.4436090290546417,
          "lp_f1": 0.3875865782012157
        },
        "test_cross_user": {
          "knn_acc": 0.4495829641819,
          "knn_f1": 0.39510697030938713,
          "lp_acc": 0.48757123947143555,
          "lp_f1": 0.37762322101162893
        }
      }
    },
    "epoch_150": {
      "layer_1": {
        "test_id": {
          "knn_acc": 0.9224250316619873,
          "knn_f1": 0.9218320527591319,
          "lp_acc": 0.5245545506477356,
          "lp_f1": 0.39053154211116914
        },
        "test_cross_device": {
          "knn_acc": 0.30038416385650635,
          "knn_f1": 0.29822367573269254,
          "lp_acc": 0.49662548303604126,
          "lp_f1": 0.3664885163017011
        },
        "test_cross_env": {
          "knn_acc": 0.3344360888004303,
          "knn_f1": 0.3252446787321299,
          "lp_acc": 0.4657142758369446,
          "lp_f1": 0.35086724288455695
        },
        "test_cross_user": {
          "knn_acc": 0.45965811610221863,
          "knn_f1": 0.4054194652485601,
          "lp_acc": 0.5011148452758789,
          "lp_f1": 0.35888252001831744
        }
      },
      "layer_3": {
        "test_id": {
          "knn_acc": 0.9395914673805237,
          "knn_f1": 0.9392068714199535,
          "lp_acc": 0.5558452606201172,
          "lp_f1": 0.4447241224429094
        },
        "test_cross_device": {
          "knn_acc": 0.2810715436935425,
          "knn_f1": 0.29657859296935796,
          "lp_acc": 0.41169142723083496,
          "lp_f1": 0.35263400503655035
        },
        "test_cross_env": {
          "knn_acc": 0.2924812138080597,
          "knn_f1": 0.3028006347314903,
          "lp_acc": 0.4526315927505493,
          "lp_f1": 0.36155274073583676
        },
        "test_cross_user": {
          "knn_acc": 0.4607316851615906,
          "knn_f1": 0.40261870168087577,
          "lp_acc": 0.5067305564880371,
          "lp_f1": 0.378792925629726
        }
      },
      "layer_6": {
        "test_id": {
          "knn_acc": 0.9493698477745056,
          "knn_f1": 0.9491626903200303,
          "lp_acc": 0.5595393180847168,
          "lp_f1": 0.47118123205951284
        },
        "test_cross_device": {
          "knn_acc": 0.28813207149505615,
          "knn_f1": 0.28106778924404485,
          "lp_acc": 0.3367251455783844,
          "lp_f1": 0.3228150946169889
        },
        "test_cross_env": {
          "knn_acc": 0.3198496103286743,
          "knn_f1": 0.30277640878914,
          "lp_acc": 0.46315789222717285,
          "lp_f1": 0.3966636932949335
        },
        "test_cross_user": {
          "knn_acc": 0.4517301321029663,
          "knn_f1": 0.39863529817340765,
          "lp_acc": 0.49302172660827637,
          "lp_f1": 0.3854415276697991
        }
      }
    },
    "epoch_200": {
      "layer_1": {
        "test_id": {
          "knn_acc": 0.9239460825920105,
          "knn_f1": 0.9233932086612648,
          "lp_acc": 0.5236853361129761,
          "lp_f1": 0.3890402818073889
        },
        "test_cross_device": {
          "knn_acc": 0.30038416385650635,
          "knn_f1": 0.2970343288182059,
          "lp_acc": 0.49517184495925903,
          "lp_f1": 0.3654096425606042
        },
        "test_cross_env": {
          "knn_acc": 0.33639097213745117,
          "knn_f1": 0.3273977327579364,
          "lp_acc": 0.4634586572647095,
          "lp_f1": 0.3495204938876774
        },
        "test_cross_user": {
          "knn_acc": 0.46560409665107727,
          "knn_f1": 0.40779913407095975,
          "lp_acc": 0.5038401484489441,
          "lp_f1": 0.36397323454286
        }
      },
      "layer_3": {
        "test_id": {
          "knn_acc": 0.9387223124504089,
          "knn_f1": 0.9383157112841606,
          "lp_acc": 0.5547587871551514,
          "lp_f1": 0.44279223814874624
        },
        "test_cross_device": {
          "knn_acc": 0.2767106294631958,
          "knn_f1": 0.29389696618313615,
          "lp_acc": 0.41979026794433594,
          "lp_f1": 0.35073106755143896
        },
        "test_cross_env": {
          "knn_acc": 0.27834585309028625,
          "knn_f1": 0.2915018859189624,
          "lp_acc": 0.4821052551269531,
          "lp_f1": 0.37928565196737746
        },
        "test_cross_user": {
          "knn_acc": 0.461392343044281,
          "knn_f1": 0.4050551031106169,
          "lp_acc": 0.5126765370368958,
          "lp_f1": 0.38851700523292065
        }
      },
      "layer_6": {
        "test_id": {
          "knn_acc": 0.9502390027046204,
          "knn_f1": 0.9500642935717563,
          "lp_acc": 0.5575836300849915,
          "lp_f1": 0.4712561590764327
        },
        "test_cross_device": {
          "knn_acc": 0.2541792094707489,
          "knn_f1": 0.2571059586007906,
          "lp_acc": 0.3094175159931183,
          "lp_f1": 0.30118480308382656
        },
        "test_cross_env": {
          "knn_acc": 0.3085714280605316,
          "knn_f1": 0.2963334163026584,
          "lp_acc": 0.4387969970703125,
          "lp_f1": 0.3746931027582201
        },
        "test_cross_user": {
          "knn_acc": 0.4494177997112274,
          "knn_f1": 0.40496107606763515,
          "lp_acc": 0.4889751374721527,
          "lp_f1": 0.39970506064842176
        }
      }
    },
    "epoch_250": {
      "layer_1": {
        "test_id": {
          "knn_acc": 0.9232942461967468,
          "knn_f1": 0.9227034315467814,
          "lp_acc": 0.525206446647644,
          "lp_f1": 0.39095258810914263
        },
        "test_cross_device": {
          "knn_acc": 0.31232479214668274,
          "knn_f1": 0.3088395748710695,
          "lp_acc": 0.5115771889686584,
          "lp_f1": 0.37121078580674827
        },
        "test_cross_env": {
          "knn_acc": 0.3366917371749878,
          "knn_f1": 0.3294293642487275,
          "lp_acc": 0.46556392312049866,
          "lp_f1": 0.34913053440256714
        },
        "test_cross_user": {
          "knn_acc": 0.46981585025787354,
          "knn_f1": 0.4108150788869122,
          "lp_acc": 0.5031794309616089,
          "lp_f1": 0.36307710246957914
        }
      },
      "layer_3": {
        "test_id": {
          "knn_acc": 0.9391568899154663,
          "knn_f1": 0.9387616290450328,
          "lp_acc": 0.5534549951553345,
          "lp_f1": 0.4405775497755296
        },
        "test_cross_device": {
          "knn_acc": 0.27484166622161865,
          "knn_f1": 0.29184480202852014,
          "lp_acc": 0.43349599838256836,
          "lp_f1": 0.3617610818214892
        },
        "test_cross_env": {
          "knn_acc": 0.27518796920776367,
          "knn_f1": 0.2876471658873886,
          "lp_acc": 0.4535338282585144,
          "lp_f1": 0.3667325176020286
        },
        "test_cross_user": {
          "knn_acc": 0.4608142673969269,
          "knn_f1": 0.4037624613917909,
          "lp_acc": 0.5122635960578918,
          "lp_f1": 0.38778116241664845
        }
      },
      "layer_6": {
        "test_id": {
          "knn_acc": 0.9487179517745972,
          "knn_f1": 0.9485365503043199,
          "lp_acc": 0.5608431100845337,
          "lp_f1": 0.4737451329499114
        },
        "test_cross_device": {
          "knn_acc": 0.2670542895793915,
          "knn_f1": 0.26646555999514576,
          "lp_acc": 0.3047451078891754,
          "lp_f1": 0.29975927244423517
        },
        "test_cross_env": {
          "knn_acc": 0.31353384256362915,
          "knn_f1": 0.29960652116635106,
          "lp_acc": 0.44150376319885254,
          "lp_f1": 0.37798464856060615
        },
        "test_cross_user": {
          "knn_acc": 0.45800644159317017,
          "knn_f1": 0.4104826561117455,
          "lp_acc": 0.48245108127593994,
          "lp_f1": 0.3922237934126981
        }
      }
    },
    "epoch_300": {
      "layer_1": {
        "test_id": {
          "knn_acc": 0.9241634011268616,
          "knn_f1": 0.9235579299132384,
          "lp_acc": 0.5215123891830444,
          "lp_f1": 0.38697793858198304
        },
        "test_cross_device": {
          "knn_acc": 0.3118056356906891,
          "knn_f1": 0.30824147021155784,
          "lp_acc": 0.5064894556999207,
          "lp_f1": 0.3687812232977952
        },
        "test_cross_env": {
          "knn_acc": 0.33609023690223694,
          "knn_f1": 0.32877235141178013,
          "lp_acc": 0.4649623930454254,
          "lp_f1": 0.3486243732471539
        },
        "test_cross_user": {
          "knn_acc": 0.4696506857872009,
          "knn_f1": 0.41070957551712733,
          "lp_acc": 0.5021884441375732,
          "lp_f1": 0.36134431487323126
        }
      },
      "layer_3": {
        "test_id": {
          "knn_acc": 0.9398087859153748,
          "knn_f1": 0.9394221066384193,
          "lp_acc": 0.5519339442253113,
          "lp_f1": 0.4389825915554406
        },
        "test_cross_device": {
          "knn_acc": 0.27411484718322754,
          "knn_f1": 0.2912570781093817,
          "lp_acc": 0.43006956577301025,
          "lp_f1": 0.36117787513351773
        },
        "test_cross_env": {
          "knn_acc": 0.27699247002601624,
          "knn_f1": 0.28951776190554634,
          "lp_acc": 0.44842106103897095,
          "lp_f1": 0.35873802371776664
        },
        "test_cross_user": {
          "knn_acc": 0.4618878662586212,
          "knn_f1": 0.4053149856557031,
          "lp_acc": 0.5125113725662231,
          "lp_f1": 0.38916330615738864
        }
      },
      "layer_6": {
        "test_id": {
          "knn_acc": 0.9502390027046204,
          "knn_f1": 0.9500498173879831,
          "lp_acc": 0.5645371675491333,
          "lp_f1": 0.4800975859130098
        },
        "test_cross_device": {
          "knn_acc": 0.24950680136680603,
          "knn_f1": 0.25143126344122413,
          "lp_acc": 0.2994496822357178,
          "lp_f1": 0.29599347149702493
        },
        "test_cross_env": {
          "knn_acc": 0.31353384256362915,
          "knn_f1": 0.3010174410077234,
          "lp_acc": 0.4273684322834015,
          "lp_f1": 0.37641563834735253
        },
        "test_cross_user": {
          "knn_acc": 0.4561896026134491,
          "knn_f1": 0.41090208751569457,
          "lp_acc": 0.4863324761390686,
          "lp_f1": 0.40162966876146683
        }
      }
    }
  }
}