{
  "exp": "mae_har_ep300_mask0.625_strategyrandom_enc6_dim128_bs128",
  "args": {
    "epochs": 300,
    "mask_ratio": 0.625,
    "encoder_depth": 6,
    "encoder_dim": 128,
    "decoder_dim": 64,
    "batch_size": 128,
    "lr": 0.00015,
    "eval_layers": "1,3,6",
    "eval_every": 50,
    "mask_strategy": "random"
  },
  "loss_log": [
    {
      "epoch": 1,
      "loss": 0.9250667403851237
    },
    {
      "epoch": 2,
      "loss": 0.492033805165972
    },
    {
      "epoch": 3,
      "loss": 0.42765916600113824
    },
    {
      "epoch": 4,
      "loss": 0.39150912651703473
    },
    {
      "epoch": 5,
      "loss": 0.33042675629258156
    },
    {
      "epoch": 6,
      "loss": 0.28239425209661323
    },
    {
      "epoch": 7,
      "loss": 0.25244957723078276
    },
    {
      "epoch": 8,
      "loss": 0.23097468433635576
    },
    {
      "epoch": 9,
      "loss": 0.21364814211570082
    },
    {
      "epoch": 10,
      "loss": 0.1963178858693157
    },
    {
      "epoch": 11,
      "loss": 0.1829657449963547
    },
    {
      "epoch": 12,
      "loss": 0.17423765086347148
    },
    {
      "epoch": 13,
      "loss": 0.16852123857963652
    },
    {
      "epoch": 14,
      "loss": 0.163890790194273
    },
    {
      "epoch": 15,
      "loss": 0.16003318982464926
    },
    {
      "epoch": 16,
      "loss": 0.1567439383694104
    },
    {
      "epoch": 17,
      "loss": 0.15400128408024708
    },
    {
      "epoch": 18,
      "loss": 0.15099045953580312
    },
    {
      "epoch": 19,
      "loss": 0.14867482689164935
    },
    {
      "epoch": 20,
      "loss": 0.14632670763170436
    },
    {
      "epoch": 21,
      "loss": 0.1441556772305852
    },
    {
      "epoch": 22,
      "loss": 0.14242892104777552
    },
    {
      "epoch": 23,
      "loss": 0.14020473736205272
    },
    {
      "epoch": 24,
      "loss": 0.1387165239346879
    },
    {
      "epoch": 25,
      "loss": 0.13681622834077903
    },
    {
      "epoch": 26,
      "loss": 0.13518539851620084
    },
    {
      "epoch": 27,
      "loss": 0.13387314527339877
    },
    {
      "epoch": 28,
      "loss": 0.13263362419924565
    },
    {
      "epoch": 29,
      "loss": 0.13151790042008674
    },
    {
      "epoch": 30,
      "loss": 0.1308907578211455
    },
    {
      "epoch": 31,
      "loss": 0.12982475012540817
    },
    {
      "epoch": 32,
      "loss": 0.1292149866709397
    },
    {
      "epoch": 33,
      "loss": 0.12875724499601693
    },
    {
      "epoch": 34,
      "loss": 0.1284402221707361
    },
    {
      "epoch": 35,
      "loss": 0.12772800658075584
    },
    {
      "epoch": 36,
      "loss": 0.1274009140297061
    },
    {
      "epoch": 37,
      "loss": 0.12719776809570335
    },
    {
      "epoch": 38,
      "loss": 0.12665920784430845
    },
    {
      "epoch": 39,
      "loss": 0.1262819150994931
    },
    {
      "epoch": 40,
      "loss": 0.12577257527127153
    },
    {
      "epoch": 41,
      "loss": 0.1254967748675318
    },
    {
      "epoch": 42,
      "loss": 0.1253597460066279
    },
    {
      "epoch": 43,
      "loss": 0.12491763232364542
    },
    {
      "epoch": 44,
      "loss": 0.12477697223602306
    },
    {
      "epoch": 45,
      "loss": 0.12447053699621133
    },
    {
      "epoch": 46,
      "loss": 0.12410983270300287
    },
    {
      "epoch": 47,
      "loss": 0.12382354507488864
    },
    {
      "epoch": 48,
      "loss": 0.1235527703982024
    },
    {
      "epoch": 49,
      "loss": 0.123138033341439
    },
    {
      "epoch": 50,
      "loss": 0.12293244042389449
    },
    {
      "epoch": 51,
      "loss": 0.12277145178190299
    },
    {
      "epoch": 52,
      "loss": 0.12241756672128326
    },
    {
      "epoch": 53,
      "loss": 0.12240337163564705
    },
    {
      "epoch": 54,
      "loss": 0.12248381790483281
    },
    {
      "epoch": 55,
      "loss": 0.12204053816163823
    },
    {
      "epoch": 56,
      "loss": 0.12197704706341028
    },
    {
      "epoch": 57,
      "loss": 0.12185145568634782
    },
    {
      "epoch": 58,
      "loss": 0.12173786852508783
    },
    {
      "epoch": 59,
      "loss": 0.12153594297844739
    },
    {
      "epoch": 60,
      "loss": 0.12142761872105655
    },
    {
      "epoch": 61,
      "loss": 0.12121700007645857
    },
    {
      "epoch": 62,
      "loss": 0.12109157624876216
    },
    {
      "epoch": 63,
      "loss": 0.1210817542547981
    },
    {
      "epoch": 64,
      "loss": 0.12081807847356513
    },
    {
      "epoch": 65,
      "loss": 0.12083986468080964
    },
    {
      "epoch": 66,
      "loss": 0.12058850435451382
    },
    {
      "epoch": 67,
      "loss": 0.12051764853476059
    },
    {
      "epoch": 68,
      "loss": 0.120457406599252
    },
    {
      "epoch": 69,
      "loss": 0.12033176639427741
    },
    {
      "epoch": 70,
      "loss": 0.11997297131234691
    },
    {
      "epoch": 71,
      "loss": 0.12014907079615764
    },
    {
      "epoch": 72,
      "loss": 0.12005304119416646
    },
    {
      "epoch": 73,
      "loss": 0.11993732108246713
    },
    {
      "epoch": 74,
      "loss": 0.11967649479352292
    },
    {
      "epoch": 75,
      "loss": 0.11974411533169803
    },
    {
      "epoch": 76,
      "loss": 0.11973198858045396
    },
    {
      "epoch": 77,
      "loss": 0.11955837532877922
    },
    {
      "epoch": 78,
      "loss": 0.11940397100434416
    },
    {
      "epoch": 79,
      "loss": 0.11934583656312454
    },
    {
      "epoch": 80,
      "loss": 0.1192269441893413
    },
    {
      "epoch": 81,
      "loss": 0.11918375641107559
    },
    {
      "epoch": 82,
      "loss": 0.11919595509590138
    },
    {
      "epoch": 83,
      "loss": 0.11912726539941061
    },
    {
      "epoch": 84,
      "loss": 0.11913001111575536
    },
    {
      "epoch": 85,
      "loss": 0.11886107296283756
    },
    {
      "epoch": 86,
      "loss": 0.11878616722034556
    },
    {
      "epoch": 87,
      "loss": 0.11897217934685093
    },
    {
      "epoch": 88,
      "loss": 0.11884984156737725
    },
    {
      "epoch": 89,
      "loss": 0.11872484016099147
    },
    {
      "epoch": 90,
      "loss": 0.11873544881209022
    },
    {
      "epoch": 91,
      "loss": 0.11879445803129957
    },
    {
      "epoch": 92,
      "loss": 0.11863288948578495
    },
    {
      "epoch": 93,
      "loss": 0.11857705652004197
    },
    {
      "epoch": 94,
      "loss": 0.1184686196169683
    },
    {
      "epoch": 95,
      "loss": 0.11840017796272323
    },
    {
      "epoch": 96,
      "loss": 0.11842663448658727
    },
    {
      "epoch": 97,
      "loss": 0.11846176353061483
    },
    {
      "epoch": 98,
      "loss": 0.1183207333974895
    },
    {
      "epoch": 99,
      "loss": 0.11836183425926027
    },
    {
      "epoch": 100,
      "loss": 0.11834698884437482
    },
    {
      "epoch": 101,
      "loss": 0.11817706979456402
    },
    {
      "epoch": 102,
      "loss": 0.1181601614558271
    },
    {
      "epoch": 103,
      "loss": 0.11824805058893703
    },
    {
      "epoch": 104,
      "loss": 0.11822238311703716
    },
    {
      "epoch": 105,
      "loss": 0.11807172829728751
    },
    {
      "epoch": 106,
      "loss": 0.11809666543489411
    },
    {
      "epoch": 107,
      "loss": 0.1180276610844192
    },
    {
      "epoch": 108,
      "loss": 0.11793998908251524
    },
    {
      "epoch": 109,
      "loss": 0.11805929536265987
    },
    {
      "epoch": 110,
      "loss": 0.11798303924678337
    },
    {
      "epoch": 111,
      "loss": 0.11803670529098738
    },
    {
      "epoch": 112,
      "loss": 0.11796821503057367
    },
    {
      "epoch": 113,
      "loss": 0.11812572150180738
    },
    {
      "epoch": 114,
      "loss": 0.11785039221424431
    },
    {
      "epoch": 115,
      "loss": 0.11803087401425555
    },
    {
      "epoch": 116,
      "loss": 0.11784390772559813
    },
    {
      "epoch": 117,
      "loss": 0.11779440021408456
    },
    {
      "epoch": 118,
      "loss": 0.11782502937352374
    },
    {
      "epoch": 119,
      "loss": 0.11780717259361631
    },
    {
      "epoch": 120,
      "loss": 0.11772024086011308
    },
    {
      "epoch": 121,
      "loss": 0.11763555720625889
    },
    {
      "epoch": 122,
      "loss": 0.11774943658106383
    },
    {
      "epoch": 123,
      "loss": 0.11758804990954343
    },
    {
      "epoch": 124,
      "loss": 0.11760453059382382
    },
    {
      "epoch": 125,
      "loss": 0.11760076911499102
    },
    {
      "epoch": 126,
      "loss": 0.11748526125614132
    },
    {
      "epoch": 127,
      "loss": 0.1176800760218785
    },
    {
      "epoch": 128,
      "loss": 0.11766306971687646
    },
    {
      "epoch": 129,
      "loss": 0.11748928026784033
    },
    {
      "epoch": 130,
      "loss": 0.11738756183712255
    },
    {
      "epoch": 131,
      "loss": 0.11742127589171841
    },
    {
      "epoch": 132,
      "loss": 0.11738490743473881
    },
    {
      "epoch": 133,
      "loss": 0.11745477831434636
    },
    {
      "epoch": 134,
      "loss": 0.11742372695534002
    },
    {
      "epoch": 135,
      "loss": 0.11752641750943094
    },
    {
      "epoch": 136,
      "loss": 0.11733414804829019
    },
    {
      "epoch": 137,
      "loss": 0.11724083959346726
    },
    {
      "epoch": 138,
      "loss": 0.11721700780271065
    },
    {
      "epoch": 139,
      "loss": 0.1173450777839337
    },
    {
      "epoch": 140,
      "loss": 0.11741919873193615
    },
    {
      "epoch": 141,
      "loss": 0.11719442903995514
    },
    {
      "epoch": 142,
      "loss": 0.11722243138189826
    },
    {
      "epoch": 143,
      "loss": 0.11717754660085553
    },
    {
      "epoch": 144,
      "loss": 0.1172034799431761
    },
    {
      "epoch": 145,
      "loss": 0.11716615612662974
    },
    {
      "epoch": 146,
      "loss": 0.11715624131084908
    },
    {
      "epoch": 147,
      "loss": 0.117098820351419
    },
    {
      "epoch": 148,
      "loss": 0.11712923233530351
    },
    {
      "epoch": 149,
      "loss": 0.1169938226008699
    },
    {
      "epoch": 150,
      "loss": 0.11716083769819566
    },
    {
      "epoch": 151,
      "loss": 0.11708811439928554
    },
    {
      "epoch": 152,
      "loss": 0.11723354627333936
    },
    {
      "epoch": 153,
      "loss": 0.11717334110289812
    },
    {
      "epoch": 154,
      "loss": 0.11707333608397416
    },
    {
      "epoch": 155,
      "loss": 0.11698382738090697
    },
    {
      "epoch": 156,
      "loss": 0.11700992237421728
    },
    {
      "epoch": 157,
      "loss": 0.11680418168682427
    },
    {
      "epoch": 158,
      "loss": 0.11684886534653958
    },
    {
      "epoch": 159,
      "loss": 0.11693000407623393
    },
    {
      "epoch": 160,
      "loss": 0.11707067529537848
    },
    {
      "epoch": 161,
      "loss": 0.11695109032804057
    },
    {
      "epoch": 162,
      "loss": 0.11685712369424957
    },
    {
      "epoch": 163,
      "loss": 0.1169524420318859
    },
    {
      "epoch": 164,
      "loss": 0.11679072185818638
    },
    {
      "epoch": 165,
      "loss": 0.11677920587715648
    },
    {
      "epoch": 166,
      "loss": 0.11682021839632875
    },
    {
      "epoch": 167,
      "loss": 0.11693139458518653
    },
    {
      "epoch": 168,
      "loss": 0.11672570782580546
    },
    {
      "epoch": 169,
      "loss": 0.11684942569228865
    },
    {
      "epoch": 170,
      "loss": 0.11693668986360232
    },
    {
      "epoch": 171,
      "loss": 0.11668816364059846
    },
    {
      "epoch": 172,
      "loss": 0.11683587902890784
    },
    {
      "epoch": 173,
      "loss": 0.11672066489145869
    },
    {
      "epoch": 174,
      "loss": 0.11668032310193494
    },
    {
      "epoch": 175,
      "loss": 0.11667910408938215
    },
    {
      "epoch": 176,
      "loss": 0.11665095074013584
    },
    {
      "epoch": 177,
      "loss": 0.11665732608664603
    },
    {
      "epoch": 178,
      "loss": 0.11667406510206915
    },
    {
      "epoch": 179,
      "loss": 0.11670818321761631
    },
    {
      "epoch": 180,
      "loss": 0.11651527863882837
    },
    {
      "epoch": 181,
      "loss": 0.11662874220027811
    },
    {
      "epoch": 182,
      "loss": 0.11669737903312558
    },
    {
      "epoch": 183,
      "loss": 0.11646880413449946
    },
    {
      "epoch": 184,
      "loss": 0.11662029585845414
    },
    {
      "epoch": 185,
      "loss": 0.11671023137335267
    },
    {
      "epoch": 186,
      "loss": 0.11658848573764165
    },
    {
      "epoch": 187,
      "loss": 0.11646046006076392
    },
    {
      "epoch": 188,
      "loss": 0.11658203726013501
    },
    {
      "epoch": 189,
      "loss": 0.11647777587530159
    },
    {
      "epoch": 190,
      "loss": 0.11649521471311648
    },
    {
      "epoch": 191,
      "loss": 0.1165310890812959
    },
    {
      "epoch": 192,
      "loss": 0.11653726002467531
    },
    {
      "epoch": 193,
      "loss": 0.11655078012318838
    },
    {
      "epoch": 194,
      "loss": 0.11646322418181669
    },
    {
      "epoch": 195,
      "loss": 0.11656499312569697
    },
    {
      "epoch": 196,
      "loss": 0.11652349117433741
    },
    {
      "epoch": 197,
      "loss": 0.1165895230979437
    },
    {
      "epoch": 198,
      "loss": 0.11654291239877541
    },
    {
      "epoch": 199,
      "loss": 0.11649111733727512
    },
    {
      "epoch": 200,
      "loss": 0.11646861844651756
    },
    {
      "epoch": 201,
      "loss": 0.11639345973907482
    },
    {
      "epoch": 202,
      "loss": 0.1164641050355775
    },
    {
      "epoch": 203,
      "loss": 0.11655092168421972
    },
    {
      "epoch": 204,
      "loss": 0.11645820679231769
    },
    {
      "epoch": 205,
      "loss": 0.1164335956176122
    },
    {
      "epoch": 206,
      "loss": 0.1163817262720494
    },
    {
      "epoch": 207,
      "loss": 0.11630729399621487
    },
    {
      "epoch": 208,
      "loss": 0.11629282585566952
    },
    {
      "epoch": 209,
      "loss": 0.11639766483789399
    },
    {
      "epoch": 210,
      "loss": 0.11641027946912107
    },
    {
      "epoch": 211,
      "loss": 0.11628411652608997
    },
    {
      "epoch": 212,
      "loss": 0.11626455063621204
    },
    {
      "epoch": 213,
      "loss": 0.11622817965135687
    },
    {
      "epoch": 214,
      "loss": 0.11630219331986848
    },
    {
      "epoch": 215,
      "loss": 0.11637325083748215
    },
    {
      "epoch": 216,
      "loss": 0.1163274177039663
    },
    {
      "epoch": 217,
      "loss": 0.11638342753230106
    },
    {
      "epoch": 218,
      "loss": 0.11626333317586354
    },
    {
      "epoch": 219,
      "loss": 0.11626958208424705
    },
    {
      "epoch": 220,
      "loss": 0.11619327962398529
    },
    {
      "epoch": 221,
      "loss": 0.11625567269289777
    },
    {
      "epoch": 222,
      "loss": 0.11616090529908736
    },
    {
      "epoch": 223,
      "loss": 0.11630349114005055
    },
    {
      "epoch": 224,
      "loss": 0.11622143159842208
    },
    {
      "epoch": 225,
      "loss": 0.116240109849189
    },
    {
      "epoch": 226,
      "loss": 0.11625421645918063
    },
    {
      "epoch": 227,
      "loss": 0.11627045761616457
    },
    {
      "epoch": 228,
      "loss": 0.11619777542849381
    },
    {
      "epoch": 229,
      "loss": 0.11625801346131734
    },
    {
      "epoch": 230,
      "loss": 0.11623314923296373
    },
    {
      "epoch": 231,
      "loss": 0.11614427396229335
    },
    {
      "epoch": 232,
      "loss": 0.11611393737118869
    },
    {
      "epoch": 233,
      "loss": 0.11607509368054923
    },
    {
      "epoch": 234,
      "loss": 0.1161216747991386
    },
    {
      "epoch": 235,
      "loss": 0.11610367965130579
    },
    {
      "epoch": 236,
      "loss": 0.11615978811113607
    },
    {
      "epoch": 237,
      "loss": 0.11599970192071937
    },
    {
      "epoch": 238,
      "loss": 0.1160810109050501
    },
    {
      "epoch": 239,
      "loss": 0.11601301025421847
    },
    {
      "epoch": 240,
      "loss": 0.11625683436258918
    },
    {
      "epoch": 241,
      "loss": 0.11601466973800034
    },
    {
      "epoch": 242,
      "loss": 0.11603870779453289
    },
    {
      "epoch": 243,
      "loss": 0.11611064044492585
    },
    {
      "epoch": 244,
      "loss": 0.11603269034198352
    },
    {
      "epoch": 245,
      "loss": 0.11606680300264131
    },
    {
      "epoch": 246,
      "loss": 0.11621684567736727
    },
    {
      "epoch": 247,
      "loss": 0.11610009844991423
    },
    {
      "epoch": 248,
      "loss": 0.11610611452765408
    },
    {
      "epoch": 249,
      "loss": 0.11607116460800171
    },
    {
      "epoch": 250,
      "loss": 0.11606110366327423
    },
    {
      "epoch": 251,
      "loss": 0.11603963583530415
    },
    {
      "epoch": 252,
      "loss": 0.1160877946143349
    },
    {
      "epoch": 253,
      "loss": 0.11605169171733516
    },
    {
      "epoch": 254,
      "loss": 0.11613252013921738
    },
    {
      "epoch": 255,
      "loss": 0.11608931373450018
    },
    {
      "epoch": 256,
      "loss": 0.11599029702622266
    },
    {
      "epoch": 257,
      "loss": 0.1160602458708343
    },
    {
      "epoch": 258,
      "loss": 0.11596508634587128
    },
    {
      "epoch": 259,
      "loss": 0.11596166067534969
    },
    {
      "epoch": 260,
      "loss": 0.11605527424918753
    },
    {
      "epoch": 261,
      "loss": 0.11611057387753612
    },
    {
      "epoch": 262,
      "loss": 0.11605730958815132
    },
    {
      "epoch": 263,
      "loss": 0.11598159953774441
    },
    {
      "epoch": 264,
      "loss": 0.11596470095572017
    },
    {
      "epoch": 265,
      "loss": 0.11596274659747169
    },
    {
      "epoch": 266,
      "loss": 0.11590741162321397
    },
    {
      "epoch": 267,
      "loss": 0.11594706654016461
    },
    {
      "epoch": 268,
      "loss": 0.11584300397052652
    },
    {
      "epoch": 269,
      "loss": 0.11607409370619626
    },
    {
      "epoch": 270,
      "loss": 0.11594316789082118
    },
    {
      "epoch": 271,
      "loss": 0.11599193571046704
    },
    {
      "epoch": 272,
      "loss": 0.1158564386091062
    },
    {
      "epoch": 273,
      "loss": 0.11597311736217567
    },
    {
      "epoch": 274,
      "loss": 0.11595532750444752
    },
    {
      "epoch": 275,
      "loss": 0.1160111300913351
    },
    {
      "epoch": 276,
      "loss": 0.11593326314219407
    },
    {
      "epoch": 277,
      "loss": 0.11588975609768004
    },
    {
      "epoch": 278,
      "loss": 0.11604955712599414
    },
    {
      "epoch": 279,
      "loss": 0.11585775177393641
    },
    {
      "epoch": 280,
      "loss": 0.11599647426711661
    },
    {
      "epoch": 281,
      "loss": 0.1158981483340973
    },
    {
      "epoch": 282,
      "loss": 0.11576566769785825
    },
    {
      "epoch": 283,
      "loss": 0.1158828509173223
    },
    {
      "epoch": 284,
      "loss": 0.11588331861864953
    },
    {
      "epoch": 285,
      "loss": 0.1159187134444004
    },
    {
      "epoch": 286,
      "loss": 0.11604887393436261
    },
    {
      "epoch": 287,
      "loss": 0.11603094557566303
    },
    {
      "epoch": 288,
      "loss": 0.11589852143966016
    },
    {
      "epoch": 289,
      "loss": 0.11587146066483997
    },
    {
      "epoch": 290,
      "loss": 0.11594398315286353
    },
    {
      "epoch": 291,
      "loss": 0.11605459017058213
    },
    {
      "epoch": 292,
      "loss": 0.1159614184871316
    },
    {
      "epoch": 293,
      "loss": 0.11591053261820759
    },
    {
      "epoch": 294,
      "loss": 0.11581133017759948
    },
    {
      "epoch": 295,
      "loss": 0.1159951803939683
    },
    {
      "epoch": 296,
      "loss": 0.11587227712429705
    },
    {
      "epoch": 297,
      "loss": 0.11598735205119565
    },
    {
      "epoch": 298,
      "loss": 0.11599586198904685
    },
    {
      "epoch": 299,
      "loss": 0.11590239591896534
    },
    {
      "epoch": 300,
      "loss": 0.11593763729823488
    }
  ],
  "evals": {
    "epoch_50": {
      "layer_1": {
        "test_id": {
          "knn_acc": 0.9365493059158325,
          "knn_f1": 0.9360391177125652,
          "lp_acc": 0.5289005041122437,
          "lp_f1": 0.391029648585794
        },
        "test_cross_device": {
          "knn_acc": 0.3329872190952301,
          "knn_f1": 0.3391492854920267,
          "lp_acc": 0.5084622502326965,
          "lp_f1": 0.3431542359118421
        },
        "test_cross_env": {
          "knn_acc": 0.3231579065322876,
          "knn_f1": 0.3203280949912602,
          "lp_acc": 0.46992480754852295,
          "lp_f1": 0.34571783407876233
        },
        "test_cross_user": {
          "knn_acc": 0.4811297357082367,
          "knn_f1": 0.40940662672678235,
          "lp_acc": 0.5013626217842102,
          "lp_f1": 0.34550066331161206
        }
      },
      "layer_3": {
        "test_id": {
          "knn_acc": 0.9474141597747803,
          "knn_f1": 0.9470488150054618,
          "lp_acc": 0.5386788249015808,
          "lp_f1": 0.4220156050144894
        },
        "test_cross_device": {
          "knn_acc": 0.20589762926101685,
          "knn_f1": 0.222738498321163,
          "lp_acc": 0.49527567625045776,
          "lp_f1": 0.35403362058231264
        },
        "test_cross_env": {
          "knn_acc": 0.2956390976905823,
          "knn_f1": 0.3049816814363112,
          "lp_acc": 0.4727819561958313,
          "lp_f1": 0.3864879204628282
        },
        "test_cross_user": {
          "knn_acc": 0.4137418568134308,
          "knn_f1": 0.3746922077343933,
          "lp_acc": 0.516723096370697,
          "lp_f1": 0.37846177803230485
        }
      },
      "layer_6": {
        "test_id": {
          "knn_acc": 0.9476314783096313,
          "knn_f1": 0.9473395113546406,
          "lp_acc": 0.5517166256904602,
          "lp_f1": 0.43664509877830715
        },
        "test_cross_device": {
          "knn_acc": 0.22645623981952667,
          "knn_f1": 0.24475006331809218,
          "lp_acc": 0.45322397351264954,
          "lp_f1": 0.3521757415005837
        },
        "test_cross_env": {
          "knn_acc": 0.3586466312408447,
          "knn_f1": 0.35108526153086617,
          "lp_acc": 0.44947367906570435,
          "lp_f1": 0.37643170892700284
        },
        "test_cross_user": {
          "knn_acc": 0.4282764792442322,
          "knn_f1": 0.38528943002362875,
          "lp_acc": 0.5042530298233032,
          "lp_f1": 0.3656361925218144
        }
      }
    },
    "epoch_100": {
      "layer_1": {
        "test_id": {
          "knn_acc": 0.9369839429855347,
          "knn_f1": 0.9366411291242602,
          "lp_acc": 0.5317253470420837,
          "lp_f1": 0.39829067002471225
        },
        "test_cross_device": {
          "knn_acc": 0.24389991164207458,
          "knn_f1": 0.25955905980300326,
          "lp_acc": 0.5114733576774597,
          "lp_f1": 0.35544474673919957
        },
        "test_cross_env": {
          "knn_acc": 0.31022557616233826,
          "knn_f1": 0.3038088054302863,
          "lp_acc": 0.47458645701408386,
          "lp_f1": 0.35592926961799387
        },
        "test_cross_user": {
          "knn_acc": 0.44305887818336487,
          "knn_f1": 0.3875019539640938,
          "lp_acc": 0.4957469701766968,
          "lp_f1": 0.33772455046669264
        }
      },
      "layer_3": {
        "test_id": {
          "knn_acc": 0.9500217437744141,
          "knn_f1": 0.9497505860233333,
          "lp_acc": 0.5488917827606201,
          "lp_f1": 0.43824596921195336
        },
        "test_cross_device": {
          "knn_acc": 0.2119198441505432,
          "knn_f1": 0.2278642104028376,
          "lp_acc": 0.473471075296402,
          "lp_f1": 0.35130935529124147
        },
        "test_cross_env": {
          "knn_acc": 0.3199999928474426,
          "knn_f1": 0.32333690264805065,
          "lp_acc": 0.43954887986183167,
          "lp_f1": 0.3519145791316702
        },
        "test_cross_user": {
          "knn_acc": 0.4068048596382141,
          "knn_f1": 0.36430483883946696,
          "lp_acc": 0.5089603066444397,
          "lp_f1": 0.37042459773680103
        }
      },
      "layer_6": {
        "test_id": {
          "knn_acc": 0.9502390027046204,
          "knn_f1": 0.9500259867008042,
          "lp_acc": 0.5482398867607117,
          "lp_f1": 0.43910452117343274
        },
        "test_cross_device": {
          "knn_acc": 0.2152424454689026,
          "knn_f1": 0.2317065092686629,
          "lp_acc": 0.4501090347766876,
          "lp_f1": 0.35401210719027554
        },
        "test_cross_env": {
          "knn_acc": 0.32616540789604187,
          "knn_f1": 0.3307378379825292,
          "lp_acc": 0.39157894253730774,
          "lp_f1": 0.35864658158637003
        },
        "test_cross_user": {
          "knn_acc": 0.4046576917171478,
          "knn_f1": 0.36978127634539776,
          "lp_acc": 0.4941778779029846,
          "lp_f1": 0.36647325727937796
        }
      }
    },
    "epoch_150": {
      "layer_1": {
        "test_id": {
          "knn_acc": 0.9395914673805237,
          "knn_f1": 0.9393082417677071,
          "lp_acc": 0.5302042365074158,
          "lp_f1": 0.39860652516590617
        },
        "test_cross_device": {
          "knn_acc": 0.24950680136680603,
          "knn_f1": 0.2644143494972584,
          "lp_acc": 0.5077354311943054,
          "lp_f1": 0.35381977930904723
        },
        "test_cross_env": {
          "knn_acc": 0.31458646059036255,
          "knn_f1": 0.3107351941385596,
          "lp_acc": 0.4703759253025055,
          "lp_f1": 0.37364122746344824
        },
        "test_cross_user": {
          "knn_acc": 0.44545379281044006,
          "knn_f1": 0.3841440616446683,
          "lp_acc": 0.4959121346473694,
          "lp_f1": 0.3390030457316244
        }
      },
      "layer_3": {
        "test_id": {
          "knn_acc": 0.9526292681694031,
          "knn_f1": 0.9523423806073088,
          "lp_acc": 0.5510647296905518,
          "lp_f1": 0.44664207624862845
        },
        "test_cross_device": {
          "knn_acc": 0.24400374293327332,
          "knn_f1": 0.26130649583278936,
          "lp_acc": 0.459973007440567,
          "lp_f1": 0.34149931693026264
        },
        "test_cross_env": {
          "knn_acc": 0.3333834707736969,
          "knn_f1": 0.33406307509198085,
          "lp_acc": 0.42887216806411743,
          "lp_f1": 0.3561906012525442
        },
        "test_cross_user": {
          "knn_acc": 0.41002559661865234,
          "knn_f1": 0.3661044176659693,
          "lp_acc": 0.5066479444503784,
          "lp_f1": 0.3672831747871767
        }
      },
      "layer_6": {
        "test_id": {
          "knn_acc": 0.9534984827041626,
          "knn_f1": 0.9532761019901337,
          "lp_acc": 0.554324209690094,
          "lp_f1": 0.4528391270048413
        },
        "test_cross_device": {
          "knn_acc": 0.2111930251121521,
          "knn_f1": 0.22599888676204732,
          "lp_acc": 0.445955753326416,
          "lp_f1": 0.3376458369774055
        },
        "test_cross_env": {
          "knn_acc": 0.2971428632736206,
          "knn_f1": 0.30343306710939427,
          "lp_acc": 0.3993985056877136,
          "lp_f1": 0.3541355153554993
        },
        "test_cross_user": {
          "knn_acc": 0.40556609630584717,
          "knn_f1": 0.36572761217336325,
          "lp_acc": 0.4892228841781616,
          "lp_f1": 0.3597190052366353
        }
      }
    },
    "epoch_200": {
      "layer_1": {
        "test_id": {
          "knn_acc": 0.9404606819152832,
          "knn_f1": 0.9401943856230844,
          "lp_acc": 0.5289005041122437,
          "lp_f1": 0.39722942180461257
        },
        "test_cross_device": {
          "knn_acc": 0.24763783812522888,
          "knn_f1": 0.2637853742392134,
          "lp_acc": 0.5107465386390686,
          "lp_f1": 0.3530952787511598
        },
        "test_cross_env": {
          "knn_acc": 0.3206014931201935,
          "knn_f1": 0.31667072237972915,
          "lp_acc": 0.4792481064796448,
          "lp_f1": 0.38082984557691335
        },
        "test_cross_user": {
          "knn_acc": 0.44528862833976746,
          "knn_f1": 0.3822203914913188,
          "lp_acc": 0.4940952956676483,
          "lp_f1": 0.3390435485034193
        }
      },
      "layer_3": {
        "test_id": {
          "knn_acc": 0.9537158012390137,
          "knn_f1": 0.9534714473475032,
          "lp_acc": 0.5562798976898193,
          "lp_f1": 0.45717844655016193
        },
        "test_cross_device": {
          "knn_acc": 0.26051291823387146,
          "knn_f1": 0.2782029537275683,
          "lp_acc": 0.46350327134132385,
          "lp_f1": 0.3430591574466407
        },
        "test_cross_env": {
          "knn_acc": 0.3357894718647003,
          "knn_f1": 0.3371866894087705,
          "lp_acc": 0.4287218153476715,
          "lp_f1": 0.35577957305740804
        },
        "test_cross_user": {
          "knn_acc": 0.4115946888923645,
          "knn_f1": 0.36821066716261,
          "lp_acc": 0.5048311352729797,
          "lp_f1": 0.3647721994054252
        }
      },
      "layer_6": {
        "test_id": {
          "knn_acc": 0.9543676376342773,
          "knn_f1": 0.9541431939965188,
          "lp_acc": 0.5597566366195679,
          "lp_f1": 0.4631123084452816
        },
        "test_cross_device": {
          "knn_acc": 0.25168725848197937,
          "knn_f1": 0.2683898537389649,
          "lp_acc": 0.47066763043403625,
          "lp_f1": 0.3488752735179611
        },
        "test_cross_env": {
          "knn_acc": 0.2923308312892914,
          "knn_f1": 0.30173872586126255,
          "lp_acc": 0.40857142210006714,
          "lp_f1": 0.35947956975040846
        },
        "test_cross_user": {
          "knn_acc": 0.4240647554397583,
          "knn_f1": 0.3783776070781141,
          "lp_acc": 0.48203814029693604,
          "lp_f1": 0.36007791164521696
        }
      }
    },
    "epoch_250": {
      "layer_1": {
        "test_id": {
          "knn_acc": 0.9411125779151917,
          "knn_f1": 0.940847739414543,
          "lp_acc": 0.5286831855773926,
          "lp_f1": 0.39766926871290587
        },
        "test_cross_device": {
          "knn_acc": 0.24524971842765808,
          "knn_f1": 0.2621182605855957,
          "lp_acc": 0.5097082257270813,
          "lp_f1": 0.35186958643557376
        },
        "test_cross_env": {
          "knn_acc": 0.3243609070777893,
          "knn_f1": 0.3199443366929626,
          "lp_acc": 0.45067667961120605,
          "lp_f1": 0.36609919126915774
        },
        "test_cross_user": {
          "knn_acc": 0.44727063179016113,
          "knn_f1": 0.3833478094602176,
          "lp_acc": 0.49541664123535156,
          "lp_f1": 0.3411453248953917
        }
      },
      "layer_3": {
        "test_id": {
          "knn_acc": 0.9537158012390137,
          "knn_f1": 0.9534365620422476,
          "lp_acc": 0.5549761056900024,
          "lp_f1": 0.4564362409835982
        },
        "test_cross_device": {
          "knn_acc": 0.25947460532188416,
          "knn_f1": 0.2756965966552738,
          "lp_acc": 0.4487592279911041,
          "lp_f1": 0.33627925927874264
        },
        "test_cross_env": {
          "knn_acc": 0.3311278223991394,
          "knn_f1": 0.33391353869205337,
          "lp_acc": 0.4272180497646332,
          "lp_f1": 0.35909965646381525
        },
        "test_cross_user": {
          "knn_acc": 0.4133289158344269,
          "knn_f1": 0.36907476184464755,
          "lp_acc": 0.5103641748428345,
          "lp_f1": 0.3747350993757189
        }
      },
      "layer_6": {
        "test_id": {
          "knn_acc": 0.9537158012390137,
          "knn_f1": 0.9534854596543976,
          "lp_acc": 0.5599738955497742,
          "lp_f1": 0.4658088009340071
        },
        "test_cross_device": {
          "knn_acc": 0.2654968202114105,
          "knn_f1": 0.28165014381710557,
          "lp_acc": 0.4701484739780426,
          "lp_f1": 0.3464433443867135
        },
        "test_cross_env": {
          "knn_acc": 0.29187971353530884,
          "knn_f1": 0.3009734140416688,
          "lp_acc": 0.4117293357849121,
          "lp_f1": 0.36461320607131575
        },
        "test_cross_user": {
          "knn_acc": 0.4287720024585724,
          "knn_f1": 0.38081975612389024,
          "lp_acc": 0.4785696566104889,
          "lp_f1": 0.35866193724596557
        }
      }
    },
    "epoch_300": {
      "layer_1": {
        "test_id": {
          "knn_acc": 0.9417644739151001,
          "knn_f1": 0.9414939651046829,
          "lp_acc": 0.5299869775772095,
          "lp_f1": 0.3989952254585148
        },
        "test_cross_device": {
          "knn_acc": 0.2425501048564911,
          "knn_f1": 0.2594169277275149,
          "lp_acc": 0.5078392624855042,
          "lp_f1": 0.3457426741905403
        },
        "test_cross_env": {
          "knn_acc": 0.324210524559021,
          "knn_f1": 0.31955100712131695,
          "lp_acc": 0.47022557258605957,
          "lp_f1": 0.3766316860933612
        },
        "test_cross_user": {
          "knn_acc": 0.4461144506931305,
          "knn_f1": 0.38274423247866235,
          "lp_acc": 0.4959947168827057,
          "lp_f1": 0.34102617303634747
        }
      },
      "layer_3": {
        "test_id": {
          "knn_acc": 0.9532811641693115,
          "knn_f1": 0.9529858689209189,
          "lp_acc": 0.5558452606201172,
          "lp_f1": 0.4564757122562754
        },
        "test_cross_device": {
          "knn_acc": 0.26051291823387146,
          "knn_f1": 0.2773750670659756,
          "lp_acc": 0.44979754090309143,
          "lp_f1": 0.33560118856365756
        },
        "test_cross_env": {
          "knn_acc": 0.3290225565433502,
          "knn_f1": 0.33231410292186875,
          "lp_acc": 0.4169924855232239,
          "lp_f1": 0.349846268414682
        },
        "test_cross_user": {
          "knn_acc": 0.4131637513637543,
          "knn_f1": 0.36902732043205366,
          "lp_acc": 0.5062350034713745,
          "lp_f1": 0.3728400396205582
        }
      },
      "layer_6": {
        "test_id": {
          "knn_acc": 0.9530639052391052,
          "knn_f1": 0.952816312150606,
          "lp_acc": 0.5638852715492249,
          "lp_f1": 0.47101880472954183
        },
        "test_cross_device": {
          "knn_acc": 0.2633163630962372,
          "knn_f1": 0.28002974085177423,
          "lp_acc": 0.45571592450141907,
          "lp_f1": 0.34608629281637343
        },
        "test_cross_env": {
          "knn_acc": 0.2935338318347931,
          "knn_f1": 0.30252806908362007,
          "lp_acc": 0.4151879847049713,
          "lp_f1": 0.36696029640509503
        },
        "test_cross_user": {
          "knn_acc": 0.42489057779312134,
          "knn_f1": 0.3782958934843202,
          "lp_acc": 0.4810471534729004,
          "lp_f1": 0.36016174087694486
        }
      }
    }
  }
}